[
  { "society_name": "Ambience Lagoon", "latitude": 28.5042, "longitude": 77.0974 },
  { "society_name": "Ardee Palm Grove Heights", "latitude": 28.4379, "longitude": 77.0811 },
  { "society_name": "Ardee The Residency", "latitude": 28.4392, "longitude": 77.0795 },
  { "society_name": "Sahara Grace", "latitude": 28.4844, "longitude": 77.0927 },
  { "society_name": "DLF Silver Oaks", "latitude": 28.4741, "longitude": 77.1004 },
  { "society_name": "Silver Oaks Estates", "latitude": 28.4289, "longitude": 77.1195 },
  { "society_name": "Emaar MGF The Vilas", "latitude": 28.4839, "longitude": 77.0874 },
  { "society_name": "DLF Belvedere Park", "latitude": 28.4908, "longitude": 77.0872 },
  { "society_name": "DLF Belvedere Towers", "latitude": 28.4915, "longitude": 77.0863 },
  { "society_name": "DLF Oakwood Estate", "latitude": 28.4842, "longitude": 77.0988 },
  { "society_name": "DLF Beverly Park", "latitude": 28.4808, "longitude": 77.0911 },
  { "society_name": "Ambience Caitriona", "latitude": 28.5064, "longitude": 77.0931 },
  { "society_name": "DLF Ridgewood Estate", "latitude": 28.4619, "longitude": 77.0875 },
  { "society_name": "DLF Regency Park 2", "latitude": 28.4682, "longitude": 77.0883 },
  { "society_name": "DLF Regency Park 1", "latitude": 28.4699, "longitude": 77.0841 },
  { "society_name": "DLF Richmond Park", "latitude": 28.4646, "longitude": 77.0894 },
  { "society_name": "DLF Westend Heights", "latitude": 28.4552, "longitude": 77.0975 },
  { "society_name": "DLF Carlton Estate", "latitude": 28.4589, "longitude": 77.0921 },
  { "society_name": "DLF Wellington Estate", "latitude": 28.4601, "longitude": 77.0910 },
  { "society_name": "DLF Princeton Estate", "latitude": 28.4574, "longitude": 77.0943 },
  { "society_name": "DLF The Pinnacle", "latitude": 28.4545, "longitude": 77.0989 },
  { "society_name": "DLF The Icon", "latitude": 28.4533, "longitude": 77.0991 },
  { "society_name": "DLF The Grove", "latitude": 28.4595, "longitude": 77.0871 },
  { "society_name": "DLF Exclusive Floors", "latitude": 28.4688, "longitude": 77.0855 },
  { "society_name": "DLF Trinity Towers", "latitude": 28.4578, "longitude": 77.0963 },
  { "society_name": "Suncity Vatsal Valley", "latitude": 28.4231, "longitude": 77.1422 },
  { "society_name": "Paras Quartier", "latitude": 28.4215, "longitude": 77.1444 },
  { "society_name": "Valley View Estate", "latitude": 28.4246, "longitude": 77.1392 },
  { "society_name": "Krrish Provence Estate", "latitude": 28.4191, "longitude": 77.1498 },
  { "society_name": "ASF Isle De Royale", "latitude": 28.4228, "longitude": 77.1531 },
  { "society_name": "Unitech Heritage City", "latitude": 28.4815, "longitude": 77.0818 },
  { "society_name": "Bedarwal Consortium Sixty Three Golf Drive", "latitude": 28.3995, "longitude": 77.0674 },
  { "society_name": "Malibu Towne", "latitude": 28.4239, "longitude": 77.0435 },
  { "society_name": "Malibu Towers", "latitude": 28.4244, "longitude": 77.0421 },
  { "society_name": "Suncity Platinum Towers", "latitude": 28.4795, "longitude": 77.0712 },
  { "society_name": "Unitech Fresco", "latitude": 28.4039, "longitude": 77.0458 },
  { "society_name": "The Close North", "latitude": 28.4081, "longitude": 77.0494 },
  { "society_name": "Unitech Escape", "latitude": 28.4022, "longitude": 77.0511 },
  { "society_name": "The Close South", "latitude": 28.4058, "longitude": 77.0522 },
  { "society_name": "Unitech Harmony", "latitude": 28.4011, "longitude": 77.0489 },
  { "society_name": "Bestech Park View Residency", "latitude": 28.5085, "longitude": 77.0392 },
  { "society_name": "Ansals Palam Vihar", "latitude": 28.5122, "longitude": 77.0364 },
  { "society_name": "Celebrity Homes", "latitude": 28.5098, "longitude": 77.0345 },
  { "society_name": "HSIIDC Sidco Shivalik Apartments", "latitude": 28.3712, "longitude": 76.9328 },
  { "society_name": "HSIIDC Sidco Aravali", "latitude": 28.3695, "longitude": 76.9311 },
  { "society_name": "Shapoorji Pallonji Joyville Gurugram", "latitude": 28.4988, "longitude": 76.9745 },
  { "society_name": "Adani M2K Oyster Grande", "latitude": 28.4995, "longitude": 76.9712 },
  { "society_name": "Emaar Imperial Gardens", "latitude": 28.4912, "longitude": 76.9535 },
  { "society_name": "Conscient Heritage Max", "latitude": 28.4925, "longitude": 76.9561 },
  { "society_name": "Emaar Gurgaon Greens", "latitude": 28.4877, "longitude": 76.9544 },
  { "society_name": "ROF Aalayas", "latitude": 28.4811, "longitude": 76.9529 },
  { "society_name": "Suncity Avenue 102", "latitude": 28.4792, "longitude": 76.9585 },
  { "society_name": "BPTP Amstoria", "latitude": 28.4932, "longitude": 76.9421 },
  { "society_name": "Adani Oyster Greens", "latitude": 28.4955, "longitude": 76.9388 },
  { "society_name": "Indiabulls Centrum Park", "latitude": 28.4764, "longitude": 76.9785 },
  { "society_name": "Signature Global Grand IVA", "latitude": 28.4722, "longitude": 76.9744 },
  { "society_name": "Satya The Hermitage", "latitude": 28.4866, "longitude": 76.9698 },
  { "society_name": "Ansal Housing Highland Park", "latitude": 28.4831, "longitude": 76.9655 },
  { "society_name": "Landmark The Residency", "latitude": 28.4815, "longitude": 76.9631 },
  { "society_name": "Hero Homes", "latitude": 28.4905, "longitude": 76.9589 },
  { "society_name": "Puri Emerald Bay", "latitude": 28.4977, "longitude": 76.9612 },
  { "society_name": "ATS Triumph", "latitude": 28.4939, "longitude": 76.9645 },
  { "society_name": "Godrej Summit", "latitude": 28.4885, "longitude": 76.9618 },
  { "society_name": "Zara Aavaas", "latitude": 28.4851, "longitude": 76.9592 },
  { "society_name": "Godrej Meridien", "latitude": 28.5088, "longitude": 76.9674 },
  { "society_name": "Paras Dews", "latitude": 28.5035, "longitude": 76.9692 },
  { "society_name": "Viridian The Plaza 106", "latitude": 28.5011, "longitude": 76.9725 },
  { "society_name": "Elan The Presidential", "latitude": 28.5054, "longitude": 76.9711 },
  { "society_name": "M3M Woodshire", "latitude": 28.5115, "longitude": 76.9622 },
  { "society_name": "Signature Global Solera", "latitude": 28.5142, "longitude": 76.9595 },
  { "society_name": "Signature Global Solera 2", "latitude": 28.5155, "longitude": 76.9581 },
  { "society_name": "Sobha City", "latitude": 28.5164, "longitude": 76.9688 },
  { "society_name": "Experion The Heartsong", "latitude": 28.5188, "longitude": 76.9554 },
  { "society_name": "Raheja Vedaanta", "latitude": 28.5205, "longitude": 76.9531 },
  { "society_name": "ROF Alante", "latitude": 28.5218, "longitude": 76.9515 },
  { "society_name": "ATS Tourmaline", "latitude": 28.4822, "longitude": 76.9912 },
  { "society_name": "ATS Kocoon", "latitude": 28.4805, "longitude": 76.9895 },
  { "society_name": "Chintels Serenity", "latitude": 28.5177, "longitude": 76.9815 },
  { "society_name": "Brisk Lumbini Terrace Homes", "latitude": 28.5152, "longitude": 76.9839 },
  { "society_name": "Raheja Atharva", "latitude": 28.5111, "longitude": 76.9874 },
  { "society_name": "SBTL Caladium", "latitude": 28.5095, "longitude": 76.9892 },
  { "society_name": "Raheja Shilas", "latitude": 28.5134, "longitude": 76.9861 },
  { "society_name": "Indiabulls Enigma", "latitude": 28.5255, "longitude": 76.9744 },
  { "society_name": "Mahindra Aura", "latitude": 28.5212, "longitude": 76.9785 },
  { "society_name": "Puri Diplomatic Greens", "latitude": 28.5241, "longitude": 76.9812 },
  { "society_name": "Tashee Capital Gateway", "latitude": 28.5268, "longitude": 76.9791 },
  { "society_name": "Kashish Manor One", "latitude": 28.5295, "longitude": 76.9768 },
  { "society_name": "Lotus Homz", "latitude": 28.5222, "longitude": 76.9721 },
  { "society_name": "M3M Crown", "latitude": 28.5201, "longitude": 76.9752 },
  { "society_name": "Experion Windchants", "latitude": 28.5288, "longitude": 76.9885 },
  { "society_name": "Tata Gurgaon Gateway", "latitude": 28.5312, "longitude": 76.9911 },
  { "society_name": "Zara Rossa", "latitude": 28.5335, "longitude": 76.9865 },
  { "society_name": "Pareena Om Apartments", "latitude": 28.5348, "longitude": 76.9841 },
  { "society_name": "La Vida by Tata Housing", "latitude": 28.5274, "longitude": 76.9952 },
  { "society_name": "M3M Capital", "latitude": 28.5239, "longitude": 76.9975 },
  { "society_name": "Smartworld One DXP", "latitude": 28.5215, "longitude": 76.9992 },
  { "society_name": "M3M Mansion", "latitude": 28.5195, "longitude": 77.0015 },
  { "society_name": "Maxworth Premier Urban", "latitude": 28.4412, "longitude": 76.9825 },
  { "society_name": "DLF Express Greens", "latitude": 28.3844, "longitude": 76.9185 },
  { "society_name": "Mittal Cosmos Executive Apartments", "latitude": 28.4974, "longitude": 77.0912 },
  { "society_name": "Ambience Creacions", "latitude": 28.4998, "longitude": 77.0865 },
  { "society_name": "Alpha Gurgaon One 22", "latitude": 28.5031, "longitude": 77.0692 },
  { "society_name": "Suncity Essel Towers", "latitude": 28.4755, "longitude": 77.0801 },
  { "society_name": "Silverglades The Ivy", "latitude": 28.4633, "longitude": 77.0935 },
  { "society_name": "Godrej Habitat", "latitude": 28.4688, "longitude": 77.0142 },
  { "society_name": "Unitech Uniworld City", "latitude": 28.4555, "longitude": 77.0425 },
  { "society_name": "Unitech The World Spa West", "latitude": 28.4512, "longitude": 77.0585 },
  { "society_name": "Raheja Atlantis", "latitude": 28.4539, "longitude": 77.0541 },
  { "society_name": "Unitech The Residences", "latitude": 28.4521, "longitude": 77.0468 },
  { "society_name": "JMD Gardens", "latitude": 28.4285, "longitude": 77.0415 },
  { "society_name": "Signature Global Park 4", "latitude": 28.2715, "longitude": 77.0612 },
  { "society_name": "Krisumi Waterfall Residences", "latitude": 28.3855, "longitude": 76.9742 },
  { "society_name": "AVL 36 Gurgaon", "latitude": 28.4352, "longitude": 76.9788 },
  { "society_name": "Imperia The Esfera", "latitude": 28.3911, "longitude": 76.9525 },
  { "society_name": "ILD Greens", "latitude": 28.3892, "longitude": 76.9554 },
  { "society_name": "Apex Our Homes", "latitude": 28.3865, "longitude": 76.9578 },
  { "society_name": "ILD Grand", "latitude": 28.3841, "longitude": 76.9595 },
  { "society_name": "Piedmont Taksila heights", "latitude": 28.3812, "longitude": 76.9615 },
  { "society_name": "Corona Optus", "latitude": 28.3935, "longitude": 76.9455 },
  { "society_name": "Ramprastha The View", "latitude": 28.3955, "longitude": 76.9412 },
  { "society_name": "Signature Global the Millennia", "latitude": 28.3972, "longitude": 76.9385 },
  { "society_name": "BPTP Terra", "latitude": 28.3888, "longitude": 76.9492 },
  { "society_name": "Ramprastha The Edge Towers", "latitude": 28.3915, "longitude": 76.9351 },
  { "society_name": "Signature Global The Millennia 2", "latitude": 28.3988, "longitude": 76.9365 },
  { "society_name": "Signature Global City", "latitude": 28.4012, "longitude": 76.9341 },
  { "society_name": "BPTP Spacio", "latitude": 28.3822, "longitude": 76.9441 },
  { "society_name": "BPTP Park Generations", "latitude": 28.3845, "longitude": 76.9415 },
  { "society_name": "BPTP Park Serene", "latitude": 28.3861, "longitude": 76.9392 },
  { "society_name": "Ramprastha Primera", "latitude": 28.3941, "longitude": 76.9322 },
  { "society_name": "Signature Global The Millennia 3", "latitude": 28.3995, "longitude": 76.9295 },
  { "society_name": "Ramprastha The Atrium", "latitude": 28.3929, "longitude": 76.9308 },
  { "society_name": "Unitech The Palms", "latitude": 28.4571, "longitude": 77.0625 },
  { "society_name": "Unitech Ivory Towers", "latitude": 28.4552, "longitude": 77.0644 },
  { "society_name": "DLF The Magnolias", "latitude": 28.4485, "longitude": 77.1082 },
  { "society_name": "DLF The Camellias", "latitude": 28.4461, "longitude": 77.1115 },
  { "society_name": "DLF The Aralias", "latitude": 28.4511, "longitude": 77.1064 },
  { "society_name": "Central Park", "latitude": 28.4422, "longitude": 77.1021 },
  { "society_name": "Ansal Maple Heights", "latitude": 28.4541, "longitude": 77.0782 },
  { "society_name": "Bancourt Apartment", "latitude": 28.4528, "longitude": 77.0805 },
  { "society_name": "Tarika Apartments", "latitude": 28.4515, "longitude": 77.0821 },
  { "society_name": "Millenium Bajrang Society", "latitude": 28.4498, "longitude": 77.0844 },
  { "society_name": "AWHO Sujjan Vihar", "latitude": 28.4535, "longitude": 77.0754 },
  { "society_name": "HBH Galaxy Apartments", "latitude": 28.4551, "longitude": 77.0729 },
  { "society_name": "Sanskriti Apartments", "latitude": 28.4568, "longitude": 77.0711 },
  { "society_name": "Shree Ganesh Apartments", "latitude": 28.4582, "longitude": 77.0695 },
  { "society_name": "Jasminium Apartment", "latitude": 28.4468, "longitude": 77.0688 },
  { "society_name": "Unitech Uniworld Gardens 2", "latitude": 28.4111, "longitude": 77.0395 },
  { "society_name": "Unitech Uniworld Gardens", "latitude": 28.4265, "longitude": 77.0451 },
  { "society_name": "Bestech Park View Spa", "latitude": 28.4241, "longitude": 77.0478 },
  { "society_name": "IRWO Westend Towers", "latitude": 28.4215, "longitude": 77.0512 },
  { "society_name": "Central Park Resorts", "latitude": 28.4255, "longitude": 77.0381 },
  { "society_name": "Vipul Greens", "latitude": 28.4168, "longitude": 77.0422 },
  { "society_name": "Parsvnath Green Ville", "latitude": 28.4144, "longitude": 77.0455 },
  { "society_name": "Central Park 2 Bellevue", "latitude": 28.4261, "longitude": 77.0375 },
  { "society_name": "Bestech Park View City", "latitude": 28.4182, "longitude": 77.0401 },
  { "society_name": "Belaperla Central Park Resorts", "latitude": 28.4272, "longitude": 77.0361 },
  { "society_name": "Central Park The Room", "latitude": 28.4281, "longitude": 77.0352 },
  { "society_name": "Central Park Resort Belgravia Residences", "latitude": 28.4292, "longitude": 77.0341 },
  { "society_name": "Vipul World", "latitude": 28.4115, "longitude": 77.0542 },
  { "society_name": "Orchid Petals", "latitude": 28.4132, "longitude": 77.0515 },
  { "society_name": "Vatika City", "latitude": 28.4155, "longitude": 77.0488 },
  { "society_name": "Bestech Park View City 2", "latitude": 28.4148, "longitude": 77.0565 },
  { "society_name": "AWHO Sispal Vihar", "latitude": 28.4095, "longitude": 77.0592 },
  { "society_name": "Omaxe The Nile", "latitude": 28.4082, "longitude": 77.0611 },
  { "society_name": "Eros Wembley Estate", "latitude": 28.4055, "longitude": 77.0642 },
  { "society_name": "SS Hibiscus", "latitude": 28.4022, "longitude": 77.0675 },
  { "society_name": "Orchid Island", "latitude": 28.4172, "longitude": 77.0712 },
  { "society_name": "Citizen apartment", "latitude": 28.4415, "longitude": 77.0725 },
  { "society_name": "Ansal API Sushant Estate", "latitude": 28.4439, "longitude": 77.0754 },
  { "society_name": "Ardee City", "latitude": 28.4385, "longitude": 77.0825 },
  { "society_name": "New Greenwood Society", "latitude": 28.4452, "longitude": 77.0611 },
  { "society_name": "Friends Apartment", "latitude": 28.4465, "longitude": 77.0588 },
  { "society_name": "EMERALD GREEN", "latitude": 28.4235, "longitude": 77.0792 },
  { "society_name": "Tulip Monsella", "latitude": 28.4312, "longitude": 77.1015 },
  { "society_name": "Parsvnath Exotica", "latitude": 28.4355, "longitude": 77.0988 },
  { "society_name": "Vipul Belmonte", "latitude": 28.4388, "longitude": 77.0955 },
  { "society_name": "TDI Ourania", "latitude": 28.4411, "longitude": 77.0921 },
  { "society_name": "DLF Park Place", "latitude": 28.4559, "longitude": 77.1012 },
  { "society_name": "DLF The Crest", "latitude": 28.4575, "longitude": 77.0995 },
  { "society_name": "DLF The Belaire", "latitude": 28.4591, "longitude": 77.0974 },
  { "society_name": "Emaar The Palm Springs", "latitude": 28.4428, "longitude": 77.0965 },
  { "society_name": "Salcon The Verandas", "latitude": 28.4455, "longitude": 77.0942 },
  { "society_name": "La Lagune", "latitude": 28.4482, "longitude": 77.0915 },
  { "society_name": "DLF The Summit", "latitude": 28.4505, "longitude": 77.0892 },
  { "society_name": "Orchid Gardens", "latitude": 28.4372, "longitude": 77.1122 },
  { "society_name": "Suncity Heights", "latitude": 28.4395, "longitude": 77.1095 },
  { "society_name": "Oasis Apartment", "latitude": 28.4421, "longitude": 77.1068 },
  { "society_name": "Kendriya Vihar", "city": "Gurgaon", "latitude": 28.4211, "longitude": 77.0945 },
  { "society_name": "CGHS HEWO Apartments", "latitude": 28.4235, "longitude": 77.0912 },
  { "society_name": "AWHO Devinder Vihar", "latitude": 28.4262, "longitude": 77.0885 },
  { "society_name": "Intelligentsia Apartment", "latitude": 28.4285, "longitude": 77.0854 },
  { "society_name": "Antriksh Royal Palm Apartments", "latitude": 28.4192, "longitude": 77.0811 },
  { "society_name": "Technocrat Society", "latitude": 28.4175, "longitude": 77.0788 },
  { "society_name": "Gail CGHS", "latitude": 28.4152, "longitude": 77.0765 },
  { "society_name": "Jalvayu Towers", "latitude": 28.4128, "longitude": 77.0742 },
  { "society_name": "Park View Apartment", "latitude": 28.4331, "longitude": 77.0655 },
  { "society_name": "Prerna Society", "latitude": 28.4352, "longitude": 77.0628 },
  { "society_name": "Alaknanda Apartments", "latitude": 28.4375, "longitude": 77.0602 },
  { "society_name": "Bhagwanti Apartment", "latitude": 28.4398, "longitude": 77.0575 },
  { "society_name": "Priyadarshini CHS", "latitude": 28.4421, "longitude": 77.0548 },
  { "society_name": "Gracious Tower", "latitude": 28.4222, "longitude": 77.1155 },
  { "society_name": "Suncity Sukriti", "latitude": 28.4245, "longitude": 77.1128 },
  { "society_name": "Suvidha Apartment", "latitude": 28.4268, "longitude": 77.1101 },
  { "society_name": "Madhur Jeevan Apartments", "latitude": 28.4291, "longitude": 77.1075 },
  { "society_name": "BPTP Freedom Park Life", "latitude": 28.4305, "longitude": 77.0522 },
  { "society_name": "Satya The Legend", "latitude": 28.4278, "longitude": 77.0555 },
  { "society_name": "IRWO Classic Apartments", "latitude": 28.4252, "longitude": 77.0588 },
  { "society_name": "Ireo The Grand Arch", "latitude": 28.4111, "longitude": 77.1025 },
  { "society_name": "Conscient Elevate", "latitude": 28.4088, "longitude": 77.1054 },
  { "society_name": "Mahindra Luminare", "latitude": 28.4062, "longitude": 77.1085 },
  { "society_name": "Raisina Residency", "latitude": 28.4035, "longitude": 77.1112 },
  { "society_name": "Pyramid Midtown", "latitude": 28.3998, "longitude": 77.1145 },
  { "society_name": "Ireo Skyon", "latitude": 28.4022, "longitude": 77.0955 },
  { "society_name": "Adani Brahma Samsara", "latitude": 28.3995, "longitude": 77.0988 },
  { "society_name": "Smart World Orchard", "latitude": 28.3968, "longitude": 77.1015 },
  { "society_name": "Pioneer Park", "latitude": 28.3922, "longitude": 77.0855 },
  { "society_name": "Smart World Orchard Street", "latitude": 28.3945, "longitude": 77.0828 },
  { "society_name": "Suposhaa Smartworld Orchard", "latitude": 28.3958, "longitude": 77.0811 },
  { "society_name": "Emaar Digihomes", "latitude": 28.3811, "longitude": 77.0925 },
  { "society_name": "Pioneer Araya", "latitude": 28.3844, "longitude": 77.0895 },
  { "society_name": "Pioneer Urban Presidia", "latitude": 28.3872, "longitude": 77.0868 },
  { "society_name": "Conscient Heritage One", "latitude": 28.3895, "longitude": 77.0841 },
  { "society_name": "Pivotal Paradise", "latitude": 28.3918, "longitude": 77.0815 },
  { "society_name": "Adani Brahma Samsara Vilasa", "latitude": 28.3932, "longitude": 77.0945 },
  { "society_name": "Adani Samsara Avasa", "latitude": 28.3911, "longitude": 77.0972 },
  { "society_name": "Signature Global Prime", "latitude": 28.3888, "longitude": 77.0995 },
  { "society_name": "Signature Global City 63A", "latitude": 28.3855, "longitude": 77.1022 },
  { "society_name": "Birla Navya", "latitude": 28.3822, "longitude": 77.1051 },
  { "society_name": "Anant Raj", "latitude": 28.3795, "longitude": 77.1082 },
  { "society_name": "Laburnum Victory Floors", "latitude": 28.3768, "longitude": 77.1111 },
  { "society_name": "TARC Ishva", "latitude": 28.3741, "longitude": 77.1139 },
  { "society_name": "M3M Heights", "latitude": 28.4065, "longitude": 77.0744 },
  { "society_name": "M3M Golfestate", "latitude": 28.4012, "longitude": 77.0795 },
  { "society_name": "Trump Tower", "latitude": 28.3988, "longitude": 77.0822 },
  { "society_name": "Emaar MGF Emerald Floors Premier", "latitude": 28.4041, "longitude": 77.0695 },
  { "society_name": "Emaar MGF Emerald Estate", "latitude": 28.4025, "longitude": 77.0718 },
  { "society_name": "M3M Skycity", "latitude": 28.4082, "longitude": 77.0721 },
  { "society_name": "Emaar Emerald Hills", "latitude": 28.4095, "longitude": 77.0688 },
  { "society_name": "M3M Latitude", "latitude": 28.3965, "longitude": 77.0655 },
  { "society_name": "M3M St Andrews", "latitude": 28.3942, "longitude": 77.0678 },
  { "society_name": "Emaar MGF The Palm Drive", "latitude": 28.4188, "longitude": 77.0841 },
  { "society_name": "Emaar Mgf Palm Terraces Select", "latitude": 28.4165, "longitude": 77.0865 },
  { "society_name": "BPTP Park Prime", "latitude": 28.4141, "longitude": 77.0892 },
  { "society_name": "Ireo Uptown", "latitude": 28.4118, "longitude": 77.0915 },
  { "society_name": "BPTP Mansions Park Prime", "latitude": 28.4101, "longitude": 77.0938 },
  { "society_name": "Emaar MGF The Enclave", "latitude": 28.4075, "longitude": 77.0961 },
  { "society_name": "M3M Merlin", "latitude": 28.3911, "longitude": 77.0585 },
  { "society_name": "Bestech Park View Spa Next", "latitude": 28.3888, "longitude": 77.0612 },
  { "society_name": "Ireo Victory Valley", "latitude": 28.3862, "longitude": 77.0639 },
  { "society_name": "Shree Vardhman Mantra", "latitude": 28.3835, "longitude": 77.0665 },
  { "society_name": "Ansal API Esencia", "latitude": 28.3805, "longitude": 77.0692 },
  { "society_name": "Ireo The Corridors", "latitude": 28.3744, "longitude": 77.0421 },
  { "society_name": "Pyramid Urban", "latitude": 28.3715, "longitude": 77.0448 },
  { "society_name": "Pareena Mi Casa", "latitude": 28.3688, "longitude": 77.0475 },
  { "society_name": "M3M The Marina", "latitude": 28.3661, "longitude": 77.0502 },
  { "society_name": "M3M Sierra 68", "latitude": 28.3634, "longitude": 77.0529 },
  { "society_name": "M3M Flora", "latitude": 28.3611, "longitude": 77.0555 },
  { "society_name": "M3M Natura", "latitude": 28.3588, "longitude": 77.0581 },
  { "society_name": "Supertech Hues", "latitude": 28.3562, "longitude": 77.0608 },
  { "society_name": "Tulip Yellow", "latitude": 28.3775, "longitude": 77.0285 },
  { "society_name": "Tulip Violet", "latitude": 28.3752, "longitude": 77.0312 },
  { "society_name": "Tulip Purple", "latitude": 28.3728, "longitude": 77.0339 },
  { "society_name": "Tulip White", "latitude": 28.3705, "longitude": 77.0365 },
  { "society_name": "Tulip Lemon", "latitude": 28.3681, "longitude": 77.0392 },
  { "society_name": "Tulip Leaf", "latitude": 28.3658, "longitude": 77.0418 },
  { "society_name": "Shree Vardhman Victoria", "latitude": 28.3622, "longitude": 77.0255 },
  { "society_name": "Tulip Orange", "latitude": 28.3599, "longitude": 77.0282 },
  { "society_name": "GPL Eden Heights", "latitude": 28.3575, "longitude": 77.0308 },
  { "society_name": "Tulip Ivory", "latitude": 28.3552, "longitude": 77.0335 },
  { "society_name": "Tulip Crimson", "latitude": 28.3528, "longitude": 77.0361 },
  { "society_name": "Pyramid Altia", "latitude": 28.3505, "longitude": 77.0388 },
  { "society_name": "Unitech Vistas", "latitude": 28.3655, "longitude": 77.0525 },
  { "society_name": "AIPL The Peaceful Homes", "latitude": 28.3682, "longitude": 77.0498 },
  { "society_name": "Paras Irene", "latitude": 28.3708, "longitude": 77.0471 },
  { "society_name": "Pyramid Fusion Homes", "latitude": 28.3735, "longitude": 77.0445 },
  { "society_name": "Pyramid Urban Homes", "latitude": 28.3761, "longitude": 77.0418 },
  { "society_name": "AIPL Zen Residences", "latitude": 28.3788, "longitude": 77.0391 },
  { "society_name": "M3M Escala", "latitude": 28.3888, "longitude": 77.0365 },
  { "society_name": "BPTP Astaire Gardens", "latitude": 28.3912, "longitude": 77.0338 },
  { "society_name": "Capital Residences 360", "latitude": 28.3938, "longitude": 77.0311 },
  { "society_name": "BPTP Pedestal", "latitude": 28.3965, "longitude": 77.0285 },
  { "society_name": "CHD Avenue 71", "latitude": 28.3981, "longitude": 77.0258 },
  { "society_name": "Signature Andour Heights", "latitude": 28.4005, "longitude": 77.0231 },
  { "society_name": "Trehan Luxury Floors 71", "latitude": 28.4028, "longitude": 77.0205 },
  { "society_name": "Tata Primanti", "latitude": 28.3925, "longitude": 77.0264 },
  { "society_name": "Spaze Privy", "latitude": 28.3952, "longitude": 77.0238 },
  { "society_name": "DLF Alameda", "latitude": 28.3844, "longitude": 77.0185 },
  { "society_name": "M3M Skywalk", "latitude": 28.3695, "longitude": 76.9855 },
  { "society_name": "Suncity Avenue 76", "latitude": 28.3672, "longitude": 76.9882 },
  { "society_name": "Pyramid Pride", "latitude": 28.3648, "longitude": 76.9908 },
  { "society_name": "Emaar MGF Palm Hills", "latitude": 28.3725, "longitude": 76.9455 },
  { "society_name": "Umang Winter Hills", "latitude": 28.3702, "longitude": 76.9482 },
  { "society_name": "Emaar Palm Heights", "latitude": 28.3678, "longitude": 76.9508 },
  { "society_name": "DLF Privana South", "latitude": 28.3655, "longitude": 76.9535 },
  { "society_name": "Umang Monsoon Breeze", "latitude": 28.3622, "longitude": 76.9562 },
  { "society_name": "Bestech Altura", "latitude": 28.3615, "longitude": 76.9944 },
  { "society_name": "Mapsko Mount Ville", "latitude": 28.3588, "longitude": 76.9971 },
  { "society_name": "Signature Global Golf Greens", "latitude": 28.3562, "longitude": 76.9998 },
  { "society_name": "Godrej Aria", "latitude": 28.3592, "longitude": 76.9815 },
  { "society_name": "Godrej 101", "latitude": 28.3568, "longitude": 76.9841 },
  { "society_name": "M3M Antalya Hills", "latitude": 28.3545, "longitude": 76.9868 },
  { "society_name": "Supertech Araville", "latitude": 28.3512, "longitude": 76.9895 },
  { "society_name": "M3M Golf Hills", "latitude": 28.3488, "longitude": 76.9922 },
  { "society_name": "Godrej Frontier", "latitude": 28.3755, "longitude": 76.9385 },
  { "society_name": "DLF The Ultima", "latitude": 28.3788, "longitude": 76.9358 },
  { "society_name": "Bestech Park View Grand Spa", "latitude": 28.3812, "longitude": 76.9331 },
  { "society_name": "Bestech Park View Ananda", "latitude": 28.3838, "longitude": 76.9305 },
  { "society_name": "Vipul Lavanya", "latitude": 28.3861, "longitude": 76.9278 },
  { "society_name": "Signature Global Synera", "latitude": 28.3885, "longitude": 76.9252 },
  { "society_name": "Signature Global City 81", "latitude": 28.3811, "longitude": 76.9422 },
  { "society_name": "Landmark The Homes 81", "latitude": 28.3835, "longitude": 76.9395 },
  { "society_name": "Vatika The Seven Lamps", "latitude": 28.3858, "longitude": 76.9368 },
  { "society_name": "Mapsko Casa Bella", "latitude": 28.3822, "longitude": 76.9515 },
  { "society_name": "Mapsko Royale Ville", "latitude": 28.3845, "longitude": 76.9488 },
  { "society_name": "DLF The Primus", "latitude": 28.3868, "longitude": 76.9461 },
  { "society_name": "Vatika Sovereign Next", "latitude": 28.3891, "longitude": 76.9435 },
  { "society_name": "Emaar Palm Gardens", "latitude": 28.3722, "longitude": 76.9644 },
  { "society_name": "Vatika Gurgaon 21", "latitude": 28.3745, "longitude": 76.9618 },
  { "society_name": "Vatika Lifestyle Homes", "latitude": 28.3768, "longitude": 76.9591 },
  { "society_name": "Mapsko Paradise", "latitude": 28.3791, "longitude": 76.9565 },
  { "society_name": "Vatika City Homes", "latitude": 28.3814, "longitude": 76.9538 },
  { "society_name": "Vatika Emilia Floors", "latitude": 28.3838, "longitude": 76.9511 },
  { "society_name": "SS Cendana Reserve Collection", "latitude": 28.3711, "longitude": 76.9745 },
  { "society_name": "Antriksh Heights", "latitude": 28.3734, "longitude": 76.9718 },
  { "society_name": "SS The Coralwood", "latitude": 28.3758, "longitude": 76.9691 },
  { "society_name": "Spaze Privy AT4", "latitude": 28.3781, "longitude": 76.9665 },
  { "society_name": "Alpha Corp GurgaonOne 84", "latitude": 28.3804, "longitude": 76.9638 },
  { "society_name": "Pivotal Devaan", "latitude": 28.3828, "longitude": 76.9611 },
  { "society_name": "SS Linden Floors", "latitude": 28.3644, "longitude": 76.9585 },
  { "society_name": "Spaze Kalistaa", "latitude": 28.3668, "longitude": 76.9558 },
  { "society_name": "SS Almeria", "latitude": 28.3691, "longitude": 76.9531 },
  { "society_name": "Godrej Air", "latitude": 28.3714, "longitude": 76.9505 },
  { "society_name": "SS The Leaf", "latitude": 28.3738, "longitude": 76.9478 },
  { "society_name": "Orris Carnation Residency", "latitude": 28.3761, "longitude": 76.9451 },
  { "society_name": "Pyramid Heights", "latitude": 28.3784, "longitude": 76.9425 },
  { "society_name": "Orris Aster Court", "latitude": 28.3611, "longitude": 76.9395 },
  { "society_name": "Orris Aster Court Premier", "latitude": 28.3634, "longitude": 76.9368 },
  { "society_name": "DLF The Skycourt", "latitude": 28.3658, "longitude": 76.9341 },
  { "society_name": "DLF New Town Heights 2", "latitude": 28.3681, "longitude": 76.9315 },
  { "society_name": "Pyramid Elite", "latitude": 28.3704, "longitude": 76.9288 },
  { "society_name": "Pyramid Urban Homes 2", "latitude": 28.3728, "longitude": 76.9261 },
  { "society_name": "Microtek Greenburg", "latitude": 28.3588, "longitude": 76.9442 },
  { "society_name": "Ansal Heights 86", "latitude": 28.3611, "longitude": 76.9415 },
  { "society_name": "County The Center Court", "latitude": 28.3634, "longitude": 76.9388 },
  { "society_name": "Adani Aangan", "latitude": 28.3522, "longitude": 76.9315 },
  { "society_name": "Godrej Oasis", "latitude": 28.3545, "longitude": 76.9288 },
  { "society_name": "Godrej Icon", "latitude": 28.3568, "longitude": 76.9261 },
  { "society_name": "Smart World Gems", "latitude": 28.3495, "longitude": 76.9485 },
  { "society_name": "M3M Soulitude", "latitude": 28.3518, "longitude": 76.9458 },
  { "society_name": "Greenopolis", "latitude": 28.3541, "longitude": 76.9431 },
  { "society_name": "Signature Global Proxima", "latitude": 28.3564, "longitude": 76.9404 },
  { "society_name": "Tulip Petals", "latitude": 28.3588, "longitude": 76.9378 },
  { "society_name": "Ace Palm Floors", "latitude": 28.3622, "longitude": 76.9515 },
  { "society_name": "Vatika Seven Elements", "latitude": 28.3645, "longitude": 76.9488 },
  { "society_name": "ATS Marigold", "latitude": 28.3668, "longitude": 76.9461 },
  { "society_name": "DLF New Town Heights 1", "latitude": 28.3488, "longitude": 76.9242 },
  { "society_name": "DLF Regal Gardens", "latitude": 28.3511, "longitude": 76.9215 },
  { "society_name": "Green Court", "latitude": 28.3534, "longitude": 76.9188 },
  { "society_name": "Shree Vardhman Flora", "latitude": 28.3558, "longitude": 76.9161 },
  { "society_name": "DLF New Town Heights", "latitude": 28.3511, "longitude": 76.9215 },
  { "society_name": "TARC Maceo", "latitude": 28.3411, "longitude": 76.9155 },
  { "society_name": "Sare Homes", "latitude": 28.3434, "longitude": 76.9128 },
  { "society_name": "Bestech Park View Sanskruti", "latitude": 28.3458, "longitude": 76.9101 },
  { "society_name": "GLS Avenue 51", "latitude": 28.3481, "longitude": 76.9075 },
  { "society_name": "Raheja Navodaya", "latitude": 28.3504, "longitude": 76.9048 },
  { "society_name": "ROF Amaltas", "latitude": 28.3528, "longitude": 76.9021 },
  { "society_name": "Signature Global City 92", "latitude": 28.3844, "longitude": 76.9085 },
  { "society_name": "Sare Crescent Parc", "latitude": 28.3868, "longitude": 76.9058 },
  { "society_name": "Raheja Sampada", "latitude": 28.3891, "longitude": 76.9031 },
  { "society_name": "Ansal Heights", "latitude": 28.3914, "longitude": 76.9004 },
  { "society_name": "Sare Petioles", "latitude": 28.3938, "longitude": 76.8978 },
  { "society_name": "DLF Garden City Floors", "latitude": 28.3961, "longitude": 76.8951 },
  { "society_name": "GLS South Avenue", "latitude": 28.3984, "longitude": 76.8925 },
  { "society_name": "Altura at DXP 92", "latitude": 28.4008, "longitude": 76.8898 },
  { "society_name": "Sare Crescent Parc Royal Greens Phase 1", "latitude": 28.3872, "longitude": 76.9051 },
  { "society_name": "Signature Global Orchard Avenue 2", "latitude": 28.3911, "longitude": 76.9155 },
  { "society_name": "MRG The Balcony", "latitude": 28.3934, "longitude": 76.9128 },
  { "society_name": "Spaze Privvy The Address", "latitude": 28.3958, "longitude": 76.9101 },
  { "society_name": "Signature Global Orchard Avenue", "latitude": 28.3911, "longitude": 76.9155 },
  { "society_name": "DLF Gardencity Enclave", "latitude": 28.3981, "longitude": 76.9074 },
  { "society_name": "Ashiana Amarah", "latitude": 28.4004, "longitude": 76.9048 },
  { "society_name": "ROF Ananda", "latitude": 28.4028, "longitude": 76.9021 },
  { "society_name": "Ramsons Kshitij", "latitude": 28.4051, "longitude": 76.8995 },
  { "society_name": "AWHO Shanti Vihar", "latitude": 28.4074, "longitude": 76.8968 },
  { "society_name": "Sidhartha NCR One Phase 1", "latitude": 28.4122, "longitude": 76.9455 },
  { "society_name": "Sidhartha NCR Greens", "latitude": 28.4145, "longitude": 76.9428 },
  { "society_name": "Signature The Roselia", "latitude": 28.4168, "longitude": 76.9401 },
  { "society_name": "Vatika Sovereign Park", "latitude": 28.4211, "longitude": 76.9385 },
  { "society_name": "Assotech Blith", "latitude": 28.4234, "longitude": 76.9358 },
  { "society_name": "Pareena Express Heights", "latitude": 28.4258, "longitude": 76.9331 },
  { "society_name": "Cosmos Express 99", "latitude": 28.4281, "longitude": 76.9304 },
  { "society_name": "Lotus Elise", "latitude": 28.4304, "longitude": 76.9278 },
  { "society_name": "Pivotal Riddhi Siddhi", "latitude": 28.4328, "longitude": 76.9251 },
  { "society_name": "Pareena Coban Residences", "latitude": 28.4351, "longitude": 76.9225 },
  { "society_name": "Pareena Laxmi Apartments", "latitude": 28.4374, "longitude": 76.9198 },
  { "society_name": "Conscient Habitat", "latitude": 28.4398, "longitude": 76.9171 },
  { "society_name": "Ashiana Mulberry Blossom", "latitude": 28.2411, "longitude": 77.0685 },
  { "society_name": "Central Park Flower Valley Aqua Front Towers", "latitude": 28.2455, "longitude": 77.0622 },
  { "society_name": "Godrej Nature Plus", "latitude": 28.2488, "longitude": 77.0595 },
  { "society_name": "Central Park Flower Valley", "latitude": 28.2444, "longitude": 77.0631 },
  { "society_name": "Central Park Flower Valley Flamingo Floors", "latitude": 28.2435, "longitude": 77.0641 },
  { "society_name": "Central Park Flower Valley Cerise Floors", "latitude": 28.2425, "longitude": 77.0651 },
  { "society_name": "Godrej Nature Plus Serenity", "latitude": 28.2492, "longitude": 77.0588 },
  { "society_name": "Silverglades The Melia", "latitude": 28.2388, "longitude": 77.0722 },
  { "society_name": "Signature Global Park", "latitude": 28.2515, "longitude": 77.0554 },
  { "society_name": "Ashiana Anmol", "latitude": 28.2538, "longitude": 77.0528 },
  { "society_name": "GLS Arawali Homes", "latitude": 28.2561, "longitude": 77.0501 },
  { "society_name": "Breez Global Heights", "latitude": 28.2584, "longitude": 77.0475 },
  { "society_name": "Signature The Serenas", "latitude": 28.2608, "longitude": 77.0448 },
  { "society_name": "Eldeco Accolade", "latitude": 28.2355, "longitude": 77.0754 },
  { "society_name": "HCBS Sports Ville", "latitude": 28.2331, "longitude": 77.0781 },
  { "society_name": "Ashiana Mulberry", "latitude": 28.2411, "longitude": 77.0685 },
  { "society_name": "MVN Athens", "latitude": 28.2288, "longitude": 77.0815 },
  { "society_name": "Trisara Our Homes 3", "latitude": 28.2265, "longitude": 77.0842 },
  { "society_name": "Breez Global Hill View", "latitude": 28.2595, "longitude": 77.0461 },
  { "society_name": "Eldeco Acclaim", "latitude": 28.2365, "longitude": 77.0741 },
  { "society_name": "Central Park Flower Valley The Room", "latitude": 28.2462, "longitude": 77.0615 },
  { "society_name": "Vipul Orchid Gardens", "latitude": 28.4372, "longitude": 77.0955 },
  { "society_name": "Ansal Sushant Apartments", "latitude": 28.4411, "longitude": 77.0785 },
  { "society_name": "Sushant Lok 1 Builder Floors", "latitude": 28.4445, "longitude": 77.0722 },
  { "society_name": "Ansal Maple Crescent", "latitude": 28.4492, "longitude": 77.0685 },
  { "society_name": "Ansal Harmony Homes", "latitude": 28.4231, "longitude": 77.0811 },
  { "society_name": "Tch Garden Residency", "latitude": 28.6111, "longitude": 77.3745 },
  { "society_name": "Spacetech Edana", "latitude": 28.4944, "longitude": 77.5115 },
  { "society_name": "Parsvnath Edens", "latitude": 28.6255, "longitude": 77.3688 },
  { "society_name": "Assotech Golf Vista Apartments", "latitude": 28.4822, "longitude": 77.5255 },
  { "society_name": "Army Flats", "latitude": 28.4715, "longitude": 77.4988 },
  { "society_name": "Presidency Heights Presithum", "latitude": 28.4111, "longitude": 77.5455 },
  { "society_name": "AVJ Homes", "latitude": 28.4866, "longitude": 77.5144 },
  { "society_name": "ultima allure", "latitude": 28.4611, "longitude": 77.5022 },
  { "society_name": "Wow Monk", "latitude": 28.4555, "longitude": 77.5311 },
  { "society_name": "Migsun Twinz", "latitude": 28.4395, "longitude": 77.5412 },
  { "society_name": "Migsun Vilaasa", "latitude": 28.4372, "longitude": 77.5435 },
  { "society_name": "SKA Metro Ville", "latitude": 28.4155, "longitude": 77.5585 },
  { "society_name": "Mahagun Manor", "latitude": 28.6188, "longitude": 77.3615 },
  { "society_name": "Twin Towers AWHO", "latitude": 28.4688, "longitude": 77.5122 },
  { "society_name": "Ambesten Twin Chalet", "latitude": 28.4522, "longitude": 77.5244 },
  { "society_name": "Trinity high street", "latitude": 28.4655, "longitude": 77.5185 },
  { "society_name": "Jaypee Greens Star Court", "latitude": 28.4744, "longitude": 77.5312 },
  { "society_name": "Jaypee Greens Moon Court", "latitude": 28.4761, "longitude": 77.5295 },
  { "society_name": "Jaypee Greens Crescent Court", "latitude": 28.4785, "longitude": 77.5268 },
  { "society_name": "Jaypee Greens The Sun Court", "latitude": 28.4812, "longitude": 77.5241 },
  { "society_name": "Jaypee The Castille", "latitude": 28.4835, "longitude": 77.5215 },
  { "society_name": "jaypee greens sea court", "latitude": 28.4858, "longitude": 77.5188 },
  { "society_name": "Jaypee Greens Spa Court", "latitude": 28.4881, "longitude": 77.5161 },
  { "society_name": "Casa View Apartment 4", "latitude": 28.4595, "longitude": 77.5352 },
  { "society_name": "Gaur 16th Avenue", "latitude": 28.5988, "longitude": 77.4412 },
  { "society_name": "Gaur 12th Avenue", "latitude": 28.6015, "longitude": 77.4385 },
  { "society_name": "Amrapali Dream Valley High Life 2", "latitude": 28.5955, "longitude": 77.4522 },
  { "society_name": "Exotica Dreamville", "latitude": 28.5931, "longitude": 77.4555 },
  { "society_name": "Galaxy North Avenue 2", "latitude": 28.6045, "longitude": 77.4322 },
  { "society_name": "French Apartments", "latitude": 28.6068, "longitude": 77.4295 },
  { "society_name": "Supertech Ecovillage 3", "latitude": 28.5811, "longitude": 77.4685 },
  { "society_name": "Galaxy Vega", "latitude": 28.5835, "longitude": 77.4658 },
  { "society_name": "Stellar One", "latitude": 28.6212, "longitude": 77.4515 },
  { "society_name": "Town Park White Orchid", "latitude": 28.6235, "longitude": 77.4488 },
  { "society_name": "Amrapali Tropical Garden", "latitude": 28.5888, "longitude": 77.4422 },
  { "society_name": "Gaur City 10Th Avenue", "latitude": 28.6115, "longitude": 77.4255 },
  { "society_name": "Geotech Pristine Avenue", "latitude": 28.6138, "longitude": 77.4228 },
  { "society_name": "Sky Gardens", "latitude": 28.6151, "longitude": 77.4205 },
  { "society_name": "Twin Celestial by Ambesten Homes", "latitude": 28.4544, "longitude": 77.5212 },
  { "society_name": "Vihaan Vista", "latitude": 28.6185, "longitude": 77.4435 },
  { "society_name": "Gayatri Life", "latitude": 28.6208, "longitude": 77.4408 },
  { "society_name": "Aig Park Avenue", "latitude": 28.6231, "longitude": 77.4381 },
  { "society_name": "Amrapali O2 Valley", "latitude": 28.5744, "longitude": 77.4855 },
  { "society_name": "SDS NRI Residency", "latitude": 28.4512, "longitude": 77.5425 },
  { "society_name": "Omaxe NRI City", "latitude": 28.4535, "longitude": 77.5398 },
  { "society_name": "Omaxe Putting Greens", "latitude": 28.4558, "longitude": 77.5371 },
  { "society_name": "ACE Divino", "latitude": 28.6188, "longitude": 77.4215 },
  { "society_name": "Ace City", "latitude": 28.6211, "longitude": 77.4188 },
  { "society_name": "ATS Rhapsody", "latitude": 28.6012, "longitude": 77.4644 },
  { "society_name": "Stellar Jeevan", "latitude": 28.6035, "longitude": 77.4618 },
  { "society_name": "Arihant Arden", "latitude": 28.6058, "longitude": 77.4591 },
  { "society_name": "CRC Sublimis", "latitude": 28.6081, "longitude": 77.4565 },
  { "society_name": "Hawelia Valencia Homes", "latitude": 28.6104, "longitude": 77.4538 },
  { "society_name": "Trident Embassy", "latitude": 28.6128, "longitude": 77.4511 },
  { "society_name": "Paramount Emotions", "latitude": 28.6151, "longitude": 77.4485 },
  { "society_name": "Apex Aura", "latitude": 28.6174, "longitude": 77.4458 },
  { "society_name": "NCR Monarch and Crown", "latitude": 28.6198, "longitude": 77.4431 },
  { "society_name": "Arihant Ambar", "latitude": 28.6221, "longitude": 77.4404 },
  { "society_name": "Trident Embassy Reso", "latitude": 28.6135, "longitude": 77.4501 },
  { "society_name": "Capital Athena", "latitude": 28.6254, "longitude": 77.4355 },
  { "society_name": "Supertech Ecovillage 1", "latitude": 28.6092, "longitude": 77.4422 },
  { "society_name": "AIGIN Royal", "latitude": 28.6115, "longitude": 77.4395 },
  { "society_name": "Apex Golf Avenue", "latitude": 28.6138, "longitude": 77.4368 },
  { "society_name": "Panchsheel Hynish", "latitude": 28.6161, "longitude": 77.4341 },
  { "society_name": "Irish Pearls", "latitude": 28.6184, "longitude": 77.4315 },
  { "society_name": "The Valley", "latitude": 28.5912, "longitude": 77.4565 },
  { "society_name": "Apex Alphabet", "latitude": 28.5935, "longitude": 77.4538 },
  { "society_name": "Lucky Krishna Elite Homes", "latitude": 28.5958, "longitude": 77.4511 },
  { "society_name": "BNH Casa View Orchid Aurum", "latitude": 28.4565, "longitude": 77.5322 },
  { "society_name": "Sportshome by Dev Sai Group", "latitude": 28.6011, "longitude": 77.4445 },
  { "society_name": "SRPL Flora Heritage", "latitude": 28.6034, "longitude": 77.4418 },
  { "society_name": "Rudra Palace Heights", "latitude": 28.6058, "longitude": 77.4391 },
  { "society_name": "Orchid Residency", "latitude": 28.6081, "longitude": 77.4365 },
  { "society_name": "Vihaan Heritage", "latitude": 28.6212, "longitude": 77.4455 },
  { "society_name": "Vihaan Greens", "latitude": 28.6235, "longitude": 77.4428 },
  { "society_name": "Vrinda Heritage Skyward", "latitude": 28.6258, "longitude": 77.4401 },
  { "society_name": "Devika Gold Homz", "latitude": 28.6281, "longitude": 77.4375 },
  { "society_name": "Rajhans Residency", "latitude": 28.6304, "longitude": 77.4348 },
  { "society_name": "Vihaan Wisteria", "latitude": 28.6328, "longitude": 77.4321 },
  { "society_name": "ATS Destinaire", "latitude": 28.6244, "longitude": 77.4611 },
  { "society_name": "SAM RISE INN", "latitude": 28.4411, "longitude": 77.5185 },
  { "society_name": "Clover Spring Homes", "latitude": 28.4435, "longitude": 77.5158 },
  { "society_name": "Lucky The Palm Valley", "latitude": 28.4458, "longitude": 77.5131 },
  { "society_name": "Vihaan Wardenia", "latitude": 28.6265, "longitude": 77.4411 },
  { "society_name": "Future Estate by FW Group", "latitude": 28.6012, "longitude": 77.4722 },
  { "society_name": "Rise Resort Residences", "latitude": 28.6035, "longitude": 77.4695 },
  { "society_name": "Express Astra", "latitude": 28.6058, "longitude": 77.4668 },
  { "society_name": "orchid aurum", "latitude": 28.4565, "longitude": 77.5322 },
  { "society_name": "Trinity Grand", "latitude": 28.4633, "longitude": 77.5155 },
  { "society_name": "HomeKraft Happy Trails", "latitude": 28.6144, "longitude": 77.4625 },
  { "society_name": "Coco County", "latitude": 28.6168, "longitude": 77.4598 },
  { "society_name": "Arihant Abode", "latitude": 28.6191, "longitude": 77.4571 },
  { "society_name": "Amaatra Homes", "latitude": 28.6214, "longitude": 77.4545 },
  { "society_name": "Mahagun Mantraa 2", "latitude": 28.4352, "longitude": 77.5512 },
  { "society_name": "Sikka Kaamya Greens", "latitude": 28.4375, "longitude": 77.5485 },
  { "society_name": "Mahagun Mantraa 1", "latitude": 28.4341, "longitude": 77.5525 },
  { "society_name": "Greater Noida Authority Apartment", "latitude": 28.4744, "longitude": 77.5111 },
  { "society_name": "3C Lotus Boulevard", "latitude": 28.5355, "longitude": 77.3712 },
  { "society_name": "3C Lotus Boulevard Espacia", "latitude": 28.5372, "longitude": 77.3695 },
  { "society_name": "ATS One Hamlet", "latitude": 28.5288, "longitude": 77.3855 },
  { "society_name": "golden residency", "latitude": 28.5312, "longitude": 77.3828 },
  { "society_name": "Chauhan Apartments", "latitude": 28.5335, "longitude": 77.3801 },
  { "society_name": "Amrapali HeartBeat City", "latitude": 28.5411, "longitude": 77.3655 },
  { "society_name": "County 107", "latitude": 28.5434, "longitude": 77.3628 },
  { "society_name": "Great Value Sharanam", "latitude": 28.5311, "longitude": 77.3915 },
  { "society_name": "3C Lotus 300", "latitude": 28.5334, "longitude": 77.3888 },
  { "society_name": "Sunworld Vanalika", "latitude": 28.5358, "longitude": 77.3861 },
  { "society_name": "Prateek Edifice", "latitude": 28.5381, "longitude": 77.3835 },
  { "society_name": "Arena The Ultima Heights", "latitude": 28.5404, "longitude": 77.3808 },
  { "society_name": "Great Value Anandam", "latitude": 28.5428, "longitude": 77.3781 },
  { "society_name": "Parx Laureate", "latitude": 28.5244, "longitude": 77.4085 },
  { "society_name": "Elixir Divine Meadows", "latitude": 28.5268, "longitude": 77.4058 },
  { "society_name": "3C Lotus Panache", "latitude": 28.5211, "longitude": 77.4012 },
  { "society_name": "Royal Residency", "latitude": 28.5234, "longitude": 77.3985 },
  { "society_name": "Ivory County", "latitude": 28.5511, "longitude": 77.4215 },
  { "society_name": "Supertech The Romano", "latitude": 28.5534, "longitude": 77.4188 },
  { "society_name": "Ajnara Ambrosia", "latitude": 28.5558, "longitude": 77.4161 },
  { "society_name": "Amrapali Platinum", "latitude": 28.5844, "longitude": 77.3585 },
  { "society_name": "Uninati The Aranya", "latitude": 28.5868, "longitude": 77.3558 },
  { "society_name": "Gaur Grandeur", "latitude": 28.5811, "longitude": 77.3685 },
  { "society_name": "Eldeco Aamantran", "latitude": 28.5834, "longitude": 77.3658 },
  { "society_name": "Eldeco Magnolia Park", "latitude": 28.5858, "longitude": 77.3631 },
  { "society_name": "Eldeco Inspire", "latitude": 28.5881, "longitude": 77.3604 },
  { "society_name": "Amrapali Zodiac", "latitude": 28.5911, "longitude": 77.3725 },
  { "society_name": "Prateek Laurel", "latitude": 28.5934, "longitude": 77.3698 },
  { "society_name": "RG Residency", "latitude": 28.5958, "longitude": 77.3671 },
  { "society_name": "ABA Cleo County", "latitude": 28.6011, "longitude": 77.3785 },
  { "society_name": "Homes 121", "latitude": 28.6034, "longitude": 77.3758 },
  { "society_name": "ABA Cleo Gold", "latitude": 28.6015, "longitude": 77.3781 },
  { "society_name": "Jaypee Greens Kalypso Court", "latitude": 28.5311, "longitude": 77.3545 },
  { "society_name": "Jaypee Greens Knights Court", "latitude": 28.5334, "longitude": 77.3518 },
  { "society_name": "Kalpataru Vista", "latitude": 28.5358, "longitude": 77.3491 },
  { "society_name": "Jaypee Greens The Pavilion Court", "latitude": 28.5381, "longitude": 77.3465 },
  { "society_name": "Jaypee Greens Imperial Court", "latitude": 28.5404, "longitude": 77.3438 },
  { "society_name": "Jaypee Greens Pavilion Heights", "latitude": 28.5428, "longitude": 77.3411 },
  { "society_name": "Jaypee Wish Town", "latitude": 28.5355, "longitude": 77.3512 },
  { "society_name": "Jaypee Augusta Town Homes", "latitude": 28.5288, "longitude": 77.3585 },
  { "society_name": "Jaypee Greens Wish Town Klassic", "latitude": 28.5211, "longitude": 77.3655 },
  { "society_name": "Jaypee Greens Kensington Boulevard", "latitude": 28.5144, "longitude": 77.3715 },
  { "society_name": "Jaypee Greens Kensington Park Apartments", "latitude": 28.5168, "longitude": 77.3688 },
  { "society_name": "Jaypee Greens Garden Isles", "latitude": 28.5092, "longitude": 77.3785 },
  { "society_name": "Jaypee Greens Kosmos", "latitude": 28.5022, "longitude": 77.3855 },
  { "society_name": "Jaypee Greens Klassic", "latitude": 28.5211, "longitude": 77.3655 },
  { "society_name": "Jaypee Klassic Shaurya", "latitude": 28.5225, "longitude": 77.3638 },
  { "society_name": "Jaypee Greens Klassic Heights", "latitude": 28.5238, "longitude": 77.3621 },
  { "society_name": "Jaypee Greens Klassic A", "latitude": 28.5211, "longitude": 77.3655 },
  { "society_name": "Jaypee Wish Point", "latitude": 28.5055, "longitude": 77.3822 },
  { "society_name": "Today Ridge Residency", "latitude": 28.4988, "longitude": 77.4122 },
  { "society_name": "Paras Tierea", "latitude": 28.5011, "longitude": 77.4095 },
  { "society_name": "Supertech Ecociti", "latitude": 28.5034, "longitude": 77.4068 },
  { "society_name": "Purvanchal Royal Park", "latitude": 28.5058, "longitude": 77.4041 },
  { "society_name": "Gulshan Vivante", "latitude": 28.5081, "longitude": 77.4014 },
  { "society_name": "Paramount Floraville", "latitude": 28.5104, "longitude": 77.3988 },
  { "society_name": "Logix Blossom County", "latitude": 28.5128, "longitude": 77.3961 },
  { "society_name": "Ajnara Daffodil", "latitude": 28.5151, "longitude": 77.3934 },
  { "society_name": "Exotica Fresco", "latitude": 28.5174, "longitude": 77.3908 },
  { "society_name": "Gulshan Ikebana", "latitude": 28.4844, "longitude": 77.4322 },
  { "society_name": "Logix Blossom Greens", "latitude": 28.4868, "longitude": 77.4295 },
  { "society_name": "Sikka Kaamna Greens", "latitude": 28.4891, "longitude": 77.4268 },
  { "society_name": "Logix Blossom Zest", "latitude": 28.4914, "longitude": 77.4241 },
  { "society_name": "SKA Orion", "latitude": 28.4938, "longitude": 77.4214 },
  { "society_name": "Rani Aakriti Shantiniketan", "latitude": 28.4961, "longitude": 77.4188 },
  { "society_name": "Sikka Karnam Greens", "latitude": 28.4984, "longitude": 77.4161 },
  { "society_name": "Gulshan Botnia", "latitude": 28.4722, "longitude": 77.4522 },
  { "society_name": "Gulshan Dynasty", "latitude": 28.4745, "longitude": 77.4495 },
  { "society_name": "Godrej Tropical Isle", "latitude": 28.4555, "longitude": 77.4688 },
  { "society_name": "ACE Parkway", "latitude": 28.4422, "longitude": 77.4855 },
  { "society_name": "ATS Pious Hideaways", "latitude": 28.4445, "longitude": 77.4828 },
  { "society_name": "Eldeco Live By The Greens", "latitude": 28.4468, "longitude": 77.4801 },
  { "society_name": "ATS Le Grandiose", "latitude": 28.4491, "longitude": 77.4775 },
  { "society_name": "Samridhi Luxuriya Avenue", "latitude": 28.4514, "longitude": 77.4748 },
  { "society_name": "ATS Pristine", "latitude": 28.4538, "longitude": 77.4721 },
  { "society_name": "Eureka Park By Tata Value Homes", "latitude": 28.4561, "longitude": 77.4695 },
  { "society_name": "ACE Golfshire", "latitude": 28.4584, "longitude": 77.4668 },
  { "society_name": "Godrej Nest", "latitude": 28.4608, "longitude": 77.4641 },
  { "society_name": "Godrej Palm Retreat", "latitude": 28.4631, "longitude": 77.4615 },
  { "society_name": "TATA Value Homes", "latitude": 28.4561, "longitude": 77.4695 },
  { "society_name": "Mahagun Meadow", "latitude": 28.4322, "longitude": 77.4985 },
  { "society_name": "Antriksh Golf City", "latitude": 28.4345, "longitude": 77.4958 },
  { "society_name": "Godrej Nurture", "latitude": 28.4368, "longitude": 77.4931 },
  { "society_name": "Antriksh Grand View", "latitude": 28.4391, "longitude": 77.4905 },
  { "society_name": "Max Antara Noida", "latitude": 28.4211, "longitude": 77.5122 },
  { "society_name": "Prateek Canary", "latitude": 28.4234, "longitude": 77.5095 },
  { "society_name": "Jaypee Aman", "latitude": 28.4111, "longitude": 77.5255 },
  { "society_name": "Ace Starlit", "latitude": 28.4144, "longitude": 77.5185 },
  { "society_name": "ATS Picturesque Reprieves", "latitude": 28.4188, "longitude": 77.5115 },
  { "society_name": "Panchsheel Greens 2", "latitude": 28.6044, "longitude": 77.4522 },
  { "society_name": "Gulshan Bellina", "latitude": 28.6068, "longitude": 77.4495 },
  { "society_name": "Nirala Aspire", "latitude": 28.6091, "longitude": 77.4468 },
  { "society_name": "SKA Divya Towers", "latitude": 28.6114, "longitude": 77.4441 },
  { "society_name": "Ratan Pearls", "latitude": 28.6138, "longitude": 77.4414 },
  { "society_name": "Victoryone Amara", "latitude": 28.6161, "longitude": 77.4388 },
  { "society_name": "Emenox La Solara", "latitude": 28.6184, "longitude": 77.4361 },
  { "society_name": "Radhey Krishna Casa Greens 1", "latitude": 28.6208, "longitude": 77.4334 },
  { "society_name": "B S Vaibhav Heritage Height", "latitude": 28.6231, "longitude": 77.4308 },
  { "society_name": "Radicon Vedantam", "latitude": 28.6254, "longitude": 77.4281 },
  { "society_name": "Aarcity Regency Park", "latitude": 28.6278, "longitude": 77.4255 },
  { "society_name": "Nirala Aspire Low Rise Phase 4", "latitude": 28.6095, "longitude": 77.4461 },
  { "society_name": "Royal Court", "latitude": 28.4988, "longitude": 77.5312 },
  { "society_name": "The Golden Palm", "latitude": 28.5111, "longitude": 77.4085 },
  { "society_name": "Paras Seasons", "latitude": 28.5155, "longitude": 77.4025 },
  { "society_name": "Sunworld Arista", "latitude": 28.5188, "longitude": 77.3988 },
  { "society_name": "3C Lotus Zing", "latitude": 28.5022, "longitude": 77.4185 },
  { "society_name": "Urbtech Xaviers", "latitude": 28.5055, "longitude": 77.4122 },
  { "society_name": "Shri Radha Sky Gardens", "latitude": 28.6185, "longitude": 77.4485 },
  { "society_name": "Ajnara Homes", "latitude": 28.6211, "longitude": 77.4452 },
  { "society_name": "Ajnara Le Garden", "latitude": 28.6235, "longitude": 77.4421 },
  { "society_name": "Supertech Oxford Square", "latitude": 28.6088, "longitude": 77.4322 },
  { "society_name": "Supertech Ecovillage 2", "latitude": 28.6011, "longitude": 77.4585 },
  { "society_name": "Panchsheel Greens", "latitude": 28.6034, "longitude": 77.4558 },
  { "society_name": "Amrapali Dream Valley", "latitude": 28.5985, "longitude": 77.4492 },
  { "society_name": "SKA Greenarch", "latitude": 28.6111, "longitude": 77.4322 },
  { "society_name": "Shri Radha Aqua Gardens", "latitude": 28.6134, "longitude": 77.4295 },
  { "society_name": "RG Luxury Homes", "latitude": 28.6158, "longitude": 77.4268 },
  { "society_name": "Anthem French Apartments", "latitude": 28.6068, "longitude": 77.4295 },
  { "society_name": "Strategic Royal Court", "latitude": 28.6112, "longitude": 77.4355 },
  { "society_name": "Gaur City 2 14th Avenue", "latitude": 28.6155, "longitude": 77.4322 },
  { "society_name": "Mahagun Mywoods Phase 1", "latitude": 28.6088, "longitude": 77.4411 },
  { "society_name": "Gaur City 2 11th Avenue", "latitude": 28.6188, "longitude": 77.4285 },
  { "society_name": "Sam Palm Olympia", "latitude": 28.6211, "longitude": 77.4255 },
  { "society_name": "Mahagun Mywoods Phase 2", "latitude": 28.6092, "longitude": 77.4405 },
  { "society_name": "Gaur City 2", "latitude": 28.6165, "longitude": 77.4311 },
  { "society_name": "Divyansh Flora", "latitude": 28.6244, "longitude": 77.4212 },
  { "society_name": "Galaxy Royale", "latitude": 28.6268, "longitude": 77.4185 },
  { "society_name": "AFOWO Raksha Addela", "latitude": 28.6291, "longitude": 77.4158 },
  { "society_name": "Sanskriti Vihar 10th Avenue", "latitude": 28.6125, "longitude": 77.4245 },
  { "society_name": "Casa Woodstock", "latitude": 28.6044, "longitude": 77.4625 },
  { "society_name": "Solitaire VVIP Homes", "latitude": 28.6068, "longitude": 77.4598 },
  { "society_name": "Mahagun Mywoods Phase 3", "latitude": 28.6098, "longitude": 77.4398 },
  { "society_name": "Wall Rock Aishwaryam", "latitude": 28.6111, "longitude": 77.4555 },
  { "society_name": "Eros Sampoornam", "latitude": 28.5912, "longitude": 77.4385 },
  { "society_name": "Nirala Greenshire", "latitude": 28.5935, "longitude": 77.4358 },
  { "society_name": "Eros Sampoornam 2", "latitude": 28.5919, "longitude": 77.4378 },
  { "society_name": "Air Force Naval Housing Board", "latitude": 28.5455, "longitude": 77.3422 },
  { "society_name": "Oasis GrandStand", "latitude": 28.3111, "longitude": 77.5455 },
  { "society_name": "YEIDA RPS 02", "latitude": 28.2988, "longitude": 77.5612 },
  { "society_name": "RWA Jalvayu Vihar", "latitude": 28.5912, "longitude": 77.3325 },
  { "society_name": "Godrej Golf Links The Suites", "latitude": 28.4411, "longitude": 77.5022 },
  { "society_name": "Godrej Golf Link Park Lane", "latitude": 28.4425, "longitude": 77.5005 },
  { "society_name": "Godrej Golf Links Windsor", "latitude": 28.4439, "longitude": 77.4988 },
  { "society_name": "The Hemisphere", "latitude": 28.4555, "longitude": 77.5111 },
  { "society_name": "Yamuna Enclave", "latitude": 28.3211, "longitude": 77.5322 },
  { "society_name": "Army Welfare", "latitude": 28.5744, "longitude": 77.3185 },
  { "society_name": "Arun Vihar", "latitude": 28.5722, "longitude": 77.3212 },
  { "society_name": "India Gate Apartment", "latitude": 28.5811, "longitude": 77.3455 },
  { "society_name": "Parsvnath Panorama", "latitude": 28.4688, "longitude": 77.5055 },
  { "society_name": "Wave Amore", "latitude": 28.5712, "longitude": 77.3411 },
  { "society_name": "Supertech 34 Pavilion", "latitude": 28.5688, "longitude": 77.3385 },
  { "society_name": "RWA Nar Vihar", "latitude": 28.5711, "longitude": 77.3425 },
  { "society_name": "Arun Vihar Noida", "latitude": 28.5722, "longitude": 77.3212 },
  { "society_name": "Army Welfare Housing", "latitude": 28.5744, "longitude": 77.3185 },
  { "society_name": "Amrapali Golf Homes", "latitude": 28.6011, "longitude": 77.4522 },
  { "society_name": "Gaur City 7th Avenue", "latitude": 28.6144, "longitude": 77.4225 },
  { "society_name": "Amrapali Centurian Park Terrace Homes", "latitude": 28.5988, "longitude": 77.4555 },
  { "society_name": "ATS Nobility", "latitude": 28.6044, "longitude": 77.4688 },
  { "society_name": "Gaur City 1st Avenue", "latitude": 28.6111, "longitude": 77.4285 },
  { "society_name": "Saya Zion", "latitude": 28.6012, "longitude": 77.4511 },
  { "society_name": "Gaur City 5th Avenue", "latitude": 28.6122, "longitude": 77.4265 },
  { "society_name": "Aastha Greens", "latitude": 28.6035, "longitude": 77.4485 },
  { "society_name": "Gaur City 6th Avenue", "latitude": 28.6134, "longitude": 77.4245 },
  { "society_name": "Aims Green Avenue", "latitude": 28.6058, "longitude": 77.4458 },
  { "society_name": "Galaxy North Avenue", "latitude": 28.6111, "longitude": 77.4295 },
  { "society_name": "Gaur City", "latitude": 28.6145, "longitude": 77.4231 },
  { "society_name": "Gaur City 4th Avenue", "latitude": 28.6118, "longitude": 77.4272 },
  { "society_name": "Godrej Woods", "latitude": 28.5588, "longitude": 77.3312 },
  { "society_name": "Pearls Gateway Towers", "latitude": 28.5611, "longitude": 77.3288 },
  { "society_name": "Defence Enclave Sector 44 Noida", "latitude": 28.5555, "longitude": 77.3355 },
  { "society_name": "Assotech Celeste Towers", "latitude": 28.5578, "longitude": 77.3328 },
  { "society_name": "Amrapali Sapphire", "latitude": 28.5644, "longitude": 77.3685 },
  { "society_name": "Prateek Stylome", "latitude": 28.5668, "longitude": 77.3658 },
  { "society_name": "Gardenia Glory", "latitude": 28.5611, "longitude": 77.3785 },
  { "society_name": "Eldeco Ananda", "latitude": 28.5588, "longitude": 77.3758 },
  { "society_name": "Sector 49 RWA", "latitude": 28.5644, "longitude": 77.3512 },
  { "society_name": "Ambience Tiverton", "latitude": 28.5711, "longitude": 77.3685 },
  { "society_name": "Amrapali Eden Park", "latitude": 28.5734, "longitude": 77.3658 },
  { "society_name": "Mahagun Morpheus", "latitude": 28.5758, "longitude": 77.3631 },
  { "society_name": "Antriksh Greens", "latitude": 28.5711, "longitude": 77.3522 },
  { "society_name": "Stellar Kings Court", "latitude": 28.5734, "longitude": 77.3495 },
  { "society_name": "Mahagun Maestro", "latitude": 28.5758, "longitude": 77.3468 },
  { "society_name": "Purvanchal Kailash Dham SAS", "latitude": 28.5744, "longitude": 77.3611 },
  { "society_name": "ATS Greens 2", "latitude": 28.5712, "longitude": 77.3635 },
  { "society_name": "TGB Meghdutam", "latitude": 28.5688, "longitude": 77.3658 },
  { "society_name": "Alok Vihar 1", "latitude": 28.5711, "longitude": 77.3555 },
  { "society_name": "Assotech Windsor Greens", "latitude": 28.5734, "longitude": 77.3528 },
  { "society_name": "ATS Greens 1", "latitude": 28.5758, "longitude": 77.3501 },
  { "society_name": "Mahagun Maple", "latitude": 28.5711, "longitude": 77.3585 },
  { "society_name": "Omaxe Twin Towers", "latitude": 28.5734, "longitude": 77.3558 },
  { "society_name": "Alok Vihar 2", "latitude": 28.5715, "longitude": 77.3545 },
  { "society_name": "Shubhkamna Appartment", "latitude": 28.5781, "longitude": 77.3435 },
  { "society_name": "Kendriya Vihar", "city": "Noida", "latitude": 28.5744, "longitude": 77.3411 },
  { "society_name": "Antriksh Nature", "latitude": 28.5844, "longitude": 77.3522 },
  { "society_name": "Arawali Apartment", "latitude": 28.5868, "longitude": 77.3495 },
  { "society_name": "Royale Garden Estate", "latitude": 28.5811, "longitude": 77.3411 },
  { "society_name": "Mapsko Krishna Apra Residency", "latitude": 28.5834, "longitude": 77.3385 },
  { "society_name": "Prateek Fedora", "latitude": 28.5858, "longitude": 77.3358 },
  { "society_name": "Gardenia Grace", "latitude": 28.5881, "longitude": 77.3331 },
  { "society_name": "Shatabdi Vihar", "latitude": 28.5822, "longitude": 77.3495 },
  { "society_name": "Indraprastha Villa", "latitude": 28.5845, "longitude": 77.3468 },
  { "society_name": "Varun Apartments", "latitude": 28.5868, "longitude": 77.3441 },
  { "society_name": "Telecom City", "latitude": 28.5811, "longitude": 77.3585 },
  { "society_name": "Purvanchal PMO Apartments", "latitude": 28.5834, "longitude": 77.3558 },
  { "society_name": "Gail Apartments", "latitude": 28.5858, "longitude": 77.3531 },
  { "society_name": "Vinayak Apartment", "latitude": 28.5881, "longitude": 77.3504 },
  { "society_name": "Pan Oasis", "latitude": 28.5911, "longitude": 77.3825 },
  { "society_name": "Elite homes", "latitude": 28.5934, "longitude": 77.3798 },
  { "society_name": "ABCZ East Avenue", "latitude": 28.5958, "longitude": 77.3771 },
  { "society_name": "Divine Home", "latitude": 28.5981, "longitude": 77.3744 },
  { "society_name": "Supertech Cape Town", "latitude": 28.5411, "longitude": 77.4085 },
  { "society_name": "Grand Ajnara Heritage", "latitude": 28.5434, "longitude": 77.4058 },
  { "society_name": "Ivy County", "latitude": 28.5511, "longitude": 77.4215 },
  { "society_name": "Golf City", "latitude": 28.5468, "longitude": 77.4012 },
  { "society_name": "Dasnac Burj Noida", "latitude": 28.5588, "longitude": 77.3825 },
  { "society_name": "Dasnac The Jewel of Noida", "latitude": 28.5611, "longitude": 77.3798 },
  { "society_name": "Apex Athena", "latitude": 28.5634, "longitude": 77.3771 },
  { "society_name": "Panchsheel Pratishtha", "latitude": 28.5658, "longitude": 77.3744 },
  { "society_name": "Gardenia Gateway", "latitude": 28.5681, "longitude": 77.3718 },
  { "society_name": "Maxblis White House", "latitude": 28.5704, "longitude": 77.3691 },
  { "society_name": "JM Aroma", "latitude": 28.5622, "longitude": 77.3885 },
  { "society_name": "Aims Golf Avenue 2", "latitude": 28.5645, "longitude": 77.3858 },
  { "society_name": "Aims Golf Avenue", "latitude": 28.5668, "longitude": 77.3831 },
  { "society_name": "Indosam75", "latitude": 28.5691, "longitude": 77.3804 },
  { "society_name": "Maxblis Grand Wellington", "latitude": 28.5714, "longitude": 77.3778 },
  { "society_name": "Maxblis Grand Kingston", "latitude": 28.5738, "longitude": 77.3751 },
  { "society_name": "Amrapali Silicon City", "latitude": 28.5611, "longitude": 77.3985 },
  { "society_name": "Amrapali Crystal Homes", "latitude": 28.5634, "longitude": 77.3958 },
  { "society_name": "Amrapali Princely Estate", "latitude": 28.5658, "longitude": 77.3931 },
  { "society_name": "Skytech Matrott", "latitude": 28.5681, "longitude": 77.3904 },
  { "society_name": "Amarpali Scilion City", "latitude": 28.5611, "longitude": 77.3985 },
  { "society_name": "JM Orchid", "latitude": 28.5522, "longitude": 77.3955 },
  { "society_name": "Sethi Max Royal", "latitude": 28.5545, "longitude": 77.3928 },
  { "society_name": "Aditya Celebrity Homes", "latitude": 28.5568, "longitude": 77.3901 },
  { "society_name": "Prateek Wisteria", "latitude": 28.5611, "longitude": 77.3815 },
  { "society_name": "Express Zenith", "latitude": 28.5634, "longitude": 77.3788 },
  { "society_name": "Antriksh Forest", "latitude": 28.5658, "longitude": 77.3761 },
  { "society_name": "Griha Pravesh", "latitude": 28.5681, "longitude": 77.3734 },
  { "society_name": "Elite Homz", "latitude": 28.5704, "longitude": 77.3708 },
  { "society_name": "Civitech Sampriti", "latitude": 28.5728, "longitude": 77.3681 },
  { "society_name": "Antriksh Kanball 3G", "latitude": 28.5751, "longitude": 77.3655 },
  { "society_name": "AVS Orchard", "latitude": 28.5774, "longitude": 77.3628 },
  { "society_name": "Mahagun Moderne", "latitude": 28.5622, "longitude": 77.4115 },
  { "society_name": "The Hyde Park", "latitude": 28.5645, "longitude": 77.4088 },
  { "society_name": "Mahagun Mezzaria", "latitude": 28.5668, "longitude": 77.4061 },
  { "society_name": "Antriksh Golf View 2", "latitude": 28.5691, "longitude": 77.4034 },
  { "society_name": "Sikka Karmic Greens", "latitude": 28.5714, "longitude": 77.4008 },
  { "society_name": "Antriksh Golf View", "latitude": 28.5691, "longitude": 77.4034 },
  { "society_name": "Aditya Urban Casa", "latitude": 28.5738, "longitude": 77.3981 },
  { "society_name": "Assotech Windsor Court", "latitude": 28.5761, "longitude": 77.3955 },
  { "society_name": "Sunshine Helios", "latitude": 28.5784, "longitude": 77.3928 },
  { "society_name": "Gaur Sports Wood", "latitude": 28.5611, "longitude": 77.4225 },
  { "society_name": "Elite Golf Greens", "latitude": 28.5634, "longitude": 77.4198 },
  { "society_name": "Civitech Stadia", "latitude": 28.5658, "longitude": 77.4171 },
  { "society_name": "Mahagun Mirabella", "latitude": 28.5681, "longitude": 77.4144 },
  { "society_name": "AWHO Vivek Vihar", "latitude": 28.4688, "longitude": 77.5111 },
  { "society_name": "CGEWHO Kendriya Vihar 2", "latitude": 28.4711, "longitude": 77.5085 },
  { "society_name": "Parsvnath Prestige", "latitude": 28.5288, "longitude": 77.3745 },
  { "society_name": "Purvanchal Silver City", "latitude": 28.5311, "longitude": 77.3718 },
  { "society_name": "Express View Apartments", "latitude": 28.5334, "longitude": 77.3691 },
  { "society_name": "Parsvnath Srishti", "latitude": 28.5358, "longitude": 77.3665 },
  { "society_name": "ATS Greens Village", "latitude": 28.5211, "longitude": 77.3985 },
  { "society_name": "Supertech Emerald Court", "latitude": 28.5234, "longitude": 77.3958 },
  { "society_name": "Eldeco Utopia", "latitude": 28.5258, "longitude": 77.3931 },
  { "society_name": "Eldeco Olympia", "latitude": 28.5281, "longitude": 77.3904 },
  { "society_name": "Grand Omaxe", "latitude": 28.5144, "longitude": 77.4115 },
  { "society_name": "Omaxe The Forest Spa", "latitude": 28.5168, "longitude": 77.4088 },
  { "society_name": "Supertech Supernova", "latitude": 28.5411, "longitude": 77.3255 },
  { "society_name": "Green View Apartment", "latitude": 28.4811, "longitude": 77.5155 },
  { "society_name": "Stellar Icon Apartments", "latitude": 28.4834, "longitude": 77.5128 },
  { "society_name": "Unitech Heights", "latitude": 28.4611, "longitude": 77.5215 },
  { "society_name": "ATS Greens Paradiso", "latitude": 28.4634, "longitude": 77.5188 },
  { "society_name": "Purvanchal Royal City", "latitude": 28.4288, "longitude": 77.5455 },
  { "society_name": "Nimbus Express Park View 2", "latitude": 28.4311, "longitude": 77.5428 },
  { "society_name": "Nimbus Express Park View 2 Low Rise", "latitude": 28.4315, "longitude": 77.5421 },
  { "society_name": "Proview Technocity Apartments", "latitude": 28.4122, "longitude": 77.5585 },
  { "society_name": "AWHO Gurjinder Vihar", "latitude": 28.4411, "longitude": 77.5312 },
  { "society_name": "Express Park View 1", "latitude": 28.4322, "longitude": 77.5215 },
  { "society_name": "Earthcon Casagrand", "latitude": 28.4345, "longitude": 77.5188 },
  { "society_name": "Casagrand 2", "latitude": 28.4355, "longitude": 77.5178 },
  { "society_name": "Omaxe Palm Greens", "latitude": 28.4511, "longitude": 77.5385 },
  { "society_name": "BHS 16 Scheme", "latitude": 28.4611, "longitude": 77.5125 },
  { "society_name": "GNIDA BHS 16", "latitude": 28.4611, "longitude": 77.5125 },
  { "society_name": "BHS 10 Scheme", "latitude": 28.4634, "longitude": 77.5098 },
  { "society_name": "Today Kings Park", "latitude": 28.4688, "longitude": 77.5185 },
  { "society_name": "Parsvnath Estate", "latitude": 28.4711, "longitude": 77.5158 },
  { "society_name": "Gaur Atulyam", "latitude": 28.4211, "longitude": 77.5522 },
  { "society_name": "Supertech Czar Suites", "latitude": 28.4555, "longitude": 77.5255 },
  { "society_name": "Eldeco Mystic Greens", "latitude": 28.4411, "longitude": 77.5312 },
  { "society_name": "Sankalp Society", "latitude": 28.4711, "longitude": 77.4915 },
  { "society_name": "GNIDA Lohiya Enclave", "latitude": 28.4734, "longitude": 77.4888 },
  { "society_name": "Migsun Ultimo", "latitude": 28.4788, "longitude": 77.4912 },
  { "society_name": "Uppal Plumeria Garden Estate", "latitude": 28.4611, "longitude": 77.5185 },
  { "society_name": "Stellar MI Citihomes", "latitude": 28.4634, "longitude": 77.5158 },
  { "society_name": "Lotus Welfare Society", "latitude": 28.4658, "longitude": 77.5131 },
  { "society_name": "CGEWHO Phase 1", "latitude": 28.4755, "longitude": 77.5012 },
  { "society_name": "Jalvayu Vihar", "latitude": 28.4788, "longitude": 77.4985 },
  { "society_name": "Anand Ashray", "latitude": 28.4811, "longitude": 77.4958 },
  { "society_name": "Novelty Himsagar Apartments", "latitude": 28.4834, "longitude": 77.4931 },
  { "society_name": "Eldeco Green Meadows", "latitude": 28.4611, "longitude": 77.5115 },
  { "society_name": "Eldeco Residency Greens", "latitude": 28.4634, "longitude": 77.5088 },
  { "society_name": "Gulmohar Estate", "latitude": 28.4658, "longitude": 77.5061 },
  { "society_name": "Unitech Horizon", "latitude": 28.4511, "longitude": 77.5215 },
  { "society_name": "Purvanchal Silver City 2", "latitude": 28.4534, "longitude": 77.5188 },
  { "society_name": "Unitech Habitat", "latitude": 28.4558, "longitude": 77.5161 },
  { "society_name": "Unitech Cascades", "latitude": 28.4581, "longitude": 77.5134 },
  { "society_name": "Paramount Golfforeste", "latitude": 28.4322, "longitude": 77.5455 },
  { "society_name": "ATS Dolce", "latitude": 28.4611, "longitude": 77.5185 },
  { "society_name": "ACE Platinum", "latitude": 28.4634, "longitude": 77.5158 },
  { "society_name": "Purvanchal Heights", "latitude": 28.4658, "longitude": 77.5131 },
  { "society_name": "Amrapali Grand", "latitude": 28.4681, "longitude": 77.5104 },
  { "society_name": "AVJ Heightss", "latitude": 28.4711, "longitude": 77.5155 },
  { "society_name": "Assotech Springfields", "latitude": 28.4734, "longitude": 77.5128 },
  { "society_name": "Victoryone Central", "latitude": 28.6188, "longitude": 77.4315 },
  { "society_name": "SKA Green Mansion", "latitude": 28.6211, "longitude": 77.4288 },
  { "society_name": "Civitech Strings", "latitude": 28.6234, "longitude": 77.4261 },
  { "society_name": "Fusion The Brook", "latitude": 28.6258, "longitude": 77.4234 },
  { "society_name": "Fusion The Rivulet", "latitude": 28.6281, "longitude": 77.4208 },
  { "society_name": "Royal Apartments", "latitude": 28.6304, "longitude": 77.4181 },
  { "society_name": "Migsun Green Mansion", "latitude": 28.6328, "longitude": 77.4154 },
  { "society_name": "Oasis Venetia Heights", "latitude": 28.6351, "longitude": 77.4128 },
  { "society_name": "Dasnac Designarch eHomes", "latitude": 28.4811, "longitude": 77.5122 },
  { "society_name": "Arenaa Heights Surajpur", "latitude": 28.4944, "longitude": 77.4915 },
  { "society_name": "Property Ultima Allure", "latitude": 28.4611, "longitude": 77.5022 },
  { "society_name": "Newtech La Galaxia", "latitude": 28.6011, "longitude": 77.4585 },
  { "society_name": "Gaur Saundaryam", "latitude": 28.6144, "longitude": 77.4225 },
  { "society_name": "Nirala Estate", "latitude": 28.6111, "longitude": 77.4285 },
  { "society_name": "NBCC Aspire Dream Valley", "latitude": 28.5985, "longitude": 77.4492 },
  { "society_name": "Amrapali Terrace Homes", "latitude": 28.6035, "longitude": 77.4485 },
  { "society_name": "Amrapali Centurian Park", "latitude": 28.5988, "longitude": 77.4555 },
  { "society_name": "ABA Cherry County", "latitude": 28.6231, "longitude": 77.4381 },
  { "society_name": "Fusion Homes", "latitude": 28.6135, "longitude": 77.4501 },
  { "society_name": "Saviour Greenarch", "latitude": 28.6111, "longitude": 77.4322 },
  { "society_name": "Nirala Estate Phase 2", "latitude": 28.6115, "longitude": 77.4281 },
  { "society_name": "Himalaya Pride", "latitude": 28.6212, "longitude": 77.4455 },
  { "society_name": "NBCC Leisure Park", "latitude": 28.6012, "longitude": 77.4722 },
  { "society_name": "Apex Splendour", "latitude": 28.5935, "longitude": 77.4538 },
  { "society_name": "Samridhi Grand Avenue", "latitude": 28.6128, "longitude": 77.4511 },
  { "society_name": "Hawelia Valenova Park", "latitude": 28.6104, "longitude": 77.4538 },
  { "society_name": "La Residentia", "latitude": 28.6068, "longitude": 77.4295 },
  { "society_name": "JM Florence", "latitude": 28.6184, "longitude": 77.4315 },
  { "society_name": "Habitech Panchtatva", "latitude": 28.6151, "longitude": 77.4485 },
  { "society_name": "Amrapali Enchante", "latitude": 28.5888, "longitude": 77.4422 },
  { "society_name": "Pigeon Spring Meadows", "latitude": 28.6188, "longitude": 77.4215 },
  { "society_name": "Amrapali Riverview", "latitude": 28.5744, "longitude": 77.4855 },
  { "society_name": "Royal Nest", "latitude": 28.6304, "longitude": 77.4348 },
  { "society_name": "Mangalya Novena Green", "latitude": 28.6161, "longitude": 77.4341 },
  { "society_name": "Patel Neotown", "latitude": 28.6254, "longitude": 77.4355 },
  { "society_name": "O2 Valley", "latitude": 28.5744, "longitude": 77.4855 },
  { "society_name": "CRC Joyous", "latitude": 28.6144, "longitude": 77.4625 },
  { "society_name": "Omkar Royal Nest", "latitude": 28.6304, "longitude": 77.4348 },
  { "society_name": "Supercity Mayfair Residency", "latitude": 28.6111, "longitude": 77.4441 },
  { "society_name": "La Residentia Amrapali", "latitude": 28.6068, "longitude": 77.4295 },
  { "society_name": "Elegant Ville", "latitude": 28.6235, "longitude": 77.4428 },
  { "society_name": "KVD Wind Park", "latitude": 28.6185, "longitude": 77.4435 },
  { "society_name": "Ace Aspire", "latitude": 28.6211, "longitude": 77.4188 },
  { "society_name": "Supertech Eco Village 1", "latitude": 28.6092, "longitude": 77.4422 },
  { "society_name": "Amrapali Verona Heights", "latitude": 28.5811, "longitude": 77.4685 },
  { "society_name": "Amrapali Dream Valley Villas", "latitude": 28.5985, "longitude": 77.4492 },
  { "society_name": "Himalya Pride", "latitude": 28.6212, "longitude": 77.4455 },
  { "society_name": "Mahagun", "latitude": 28.6188, "longitude": 77.3615 },
  { "society_name": "Gaur Yamuna City 16th Park View", "latitude": 28.2988, "longitude": 77.5455 },
  { "society_name": "ATS Allure", "latitude": 28.2811, "longitude": 77.5612 },
  { "society_name": "Gaur Yamuna City", "latitude": 28.2988, "longitude": 77.5455 },
  { "society_name": "Royal Hometown Beetle Lap", "latitude": 28.3111, "longitude": 77.5322 },
  { "society_name": "Yamuna Expressway Authority Flat", "latitude": 28.2744, "longitude": 77.5511 },
  { "society_name": "Ajnara Panorama", "latitude": 28.2611, "longitude": 77.5685 },
  { "society_name": "Solitairian City", "latitude": 28.2588, "longitude": 77.5712 },
  { "society_name": "Supertech Golf Country", "latitude": 28.2455, "longitude": 77.5855 },
  { "society_name": "Gaur Green Avenue", "latitude": 28.6355, "longitude": 77.3712 },
  { "society_name": "ATS Advantage", "latitude": 28.6372, "longitude": 77.3695 },
  { "society_name": "ABA Corp Orange County", "latitude": 28.6311, "longitude": 77.3855 },
  { "society_name": "Shipra Krishna Vista", "latitude": 28.6335, "longitude": 77.3828 },
  { "society_name": "Rajhans Premier Apartment", "latitude": 28.6358, "longitude": 77.3801 },
  { "society_name": "Shipra Srishti", "latitude": 28.6381, "longitude": 77.3745 },
  { "society_name": "Jaipurias Sunrise Greens", "latitude": 28.6404, "longitude": 77.3718 },
  { "society_name": "Niho Scottish Garden", "latitude": 28.6428, "longitude": 77.3688 },
  { "society_name": "Trine Towers", "latitude": 28.6451, "longitude": 77.3655 },
  { "society_name": "Angel Jupiter", "latitude": 28.6311, "longitude": 77.3915 },
  { "society_name": "Saya Zenith", "latitude": 28.6334, "longitude": 77.3888 },
  { "society_name": "Ashiana Greens", "latitude": 28.6358, "longitude": 77.3861 },
  { "society_name": "Apex D Rio", "latitude": 28.6381, "longitude": 77.3835 },
  { "society_name": "Ashiana Upvan", "latitude": 28.6404, "longitude": 77.3808 },
  { "society_name": "Gaur Valerio", "latitude": 28.6428, "longitude": 77.3781 },
  { "society_name": "SVP Gulmohur Residency", "latitude": 28.6451, "longitude": 77.3754 },
  { "society_name": "Exotica Elegance", "latitude": 28.6474, "longitude": 77.3728 },
  { "society_name": "Divyansh Pratham", "latitude": 28.6498, "longitude": 77.3701 },
  { "society_name": "JKG Amba G Residency", "latitude": 28.6521, "longitude": 77.3674 },
  { "society_name": "Shri Balaji Residency", "latitude": 28.6544, "longitude": 77.3648 },
  { "society_name": "Manchanda East End Apartments", "latitude": 28.6568, "longitude": 77.3621 },
  { "society_name": "Oxirich Avenue", "latitude": 28.6591, "longitude": 77.3595 },
  { "society_name": "Charms Solitaire", "latitude": 28.6614, "longitude": 77.3568 },
  { "society_name": "Nirala Eden Park", "latitude": 28.6638, "longitude": 77.3541 },
  { "society_name": "Saya Desire Residency", "latitude": 28.6661, "longitude": 77.3515 },
  { "society_name": "Vashisth Vijaya Apartment", "latitude": 28.6684, "longitude": 77.3488 },
  { "society_name": "Himalayan Towers", "latitude": 28.6708, "longitude": 77.3461 },
  { "society_name": "DLF Ankur Vihar", "latitude": 28.7188, "longitude": 77.2915 },
  { "society_name": "Rail Vihar", "latitude": 28.7211, "longitude": 77.2888 },
  { "society_name": "SLF Ved Vihar", "latitude": 28.7234, "longitude": 77.2861 },
  { "society_name": "Aditya Luxuria Estate", "latitude": 28.6855, "longitude": 77.4422 },
  { "society_name": "Bharat City", "latitude": 28.6878, "longitude": 77.4395 },
  { "society_name": "Super Realtech Oxy Homez", "latitude": 28.6901, "longitude": 77.4368 },
  { "society_name": "Andromida Planet One", "latitude": 28.6924, "longitude": 77.4341 },
  { "society_name": "MR Delhi 99", "latitude": 28.6948, "longitude": 77.4315 },
  { "society_name": "DLF Dilshad Ext Sahibabad", "latitude": 28.6744, "longitude": 77.3355 },
  { "society_name": "Panchsheel Wellington", "latitude": 28.6411, "longitude": 77.4485 },
  { "society_name": "Paramount Symphony", "latitude": 28.6434, "longitude": 77.4458 },
  { "society_name": "Ajnara Gen 10", "latitude": 28.6458, "longitude": 77.4431 },
  { "society_name": "Mahagun Mascot", "latitude": 28.6481, "longitude": 77.4404 },
  { "society_name": "Supertech Livingston", "latitude": 28.6504, "longitude": 77.4378 },
  { "society_name": "Assotech The Nest", "latitude": 28.6528, "longitude": 77.4351 },
  { "society_name": "Gardenia Square 1", "latitude": 28.6551, "longitude": 77.4325 },
  { "society_name": "GH 7", "latitude": 28.6574, "longitude": 77.4298 },
  { "society_name": "Gaur Global Village", "latitude": 28.6598, "longitude": 77.4271 },
  { "society_name": "Bulland Heights", "latitude": 28.6621, "longitude": 77.4245 },
  { "society_name": "Prateek The Royal Cliff", "latitude": 28.6644, "longitude": 77.4218 },
  { "society_name": "Proview Laboni Apartments", "latitude": 28.6668, "longitude": 77.4191 },
  { "society_name": "Prabhat Heights", "latitude": 28.6691, "longitude": 77.4165 },
  { "society_name": "Saviour IRIS", "latitude": 28.6714, "longitude": 77.4138 },
  { "society_name": "Arocon Golf Ville", "latitude": 28.6738, "longitude": 77.4111 },
  { "society_name": "Exotica Eastern Court", "latitude": 28.6761, "longitude": 77.4085 },
  { "society_name": "Renowned Srishti", "latitude": 28.6784, "longitude": 77.4058 },
  { "society_name": "Skytech Merion Residency", "latitude": 28.6808, "longitude": 77.4031 },
  { "society_name": "Sam Clement City", "latitude": 28.6831, "longitude": 77.4005 },
  { "society_name": "Dreamland The Willows", "latitude": 28.6854, "longitude": 77.3978 },
  { "society_name": "KSN Golf Greens", "latitude": 28.6878, "longitude": 77.3951 },
  { "society_name": "Arihant Ambience", "latitude": 28.6901, "longitude": 77.3925 },
  { "society_name": "Balaji Foster Heights", "latitude": 28.6924, "longitude": 77.3898 },
  { "society_name": "SKB Gold Coast", "latitude": 28.6948, "longitude": 77.3871 },
  { "society_name": "Landcraft MetroHomes", "latitude": 28.6822, "longitude": 77.4585 },
  { "society_name": "Amrapali Empire", "latitude": 28.6845, "longitude": 77.4558 },
  { "society_name": "Keltech Kumar Golf Vista", "latitude": 28.6868, "longitude": 77.4531 },
  { "society_name": "Cosmos Golden Heights", "latitude": 28.6891, "longitude": 77.4504 },
  { "society_name": "Balaji Enclave", "latitude": 28.6914, "longitude": 77.4478 },
  { "society_name": "Shipra Riviera", "latitude": 28.6411, "longitude": 77.3685 },
  { "society_name": "Cloud 9", "latitude": 28.6434, "longitude": 77.3658 },
  { "society_name": "Parsvnath Majestic", "latitude": 28.6458, "longitude": 77.3631 },
  { "society_name": "Angel Mercury Indirapuram", "latitude": 28.6481, "longitude": 77.3604 },
  { "society_name": "MKS La Royale", "latitude": 28.6504, "longitude": 77.3578 },
  { "society_name": "Pinnacle Towers", "latitude": 28.6528, "longitude": 77.3551 },
  { "society_name": "Ramprastha Imperial Heights", "latitude": 28.6551, "longitude": 77.3525 },
  { "society_name": "Amrapali Village 2", "latitude": 28.6574, "longitude": 77.3498 },
  { "society_name": "Arihant Harmony", "latitude": 28.6598, "longitude": 77.3471 },
  { "society_name": "Rishabh Cloud9 Skylish Towers", "latitude": 28.6621, "longitude": 77.3445 },
  { "society_name": "Shipra Sun Tower", "latitude": 28.6411, "longitude": 77.3685 },
  { "society_name": "Shipra Windsor and Nova Society", "latitude": 28.6434, "longitude": 77.3658 },
  { "society_name": "Independent Builder Floors Indirapuram", "latitude": 28.6455, "longitude": 77.3622 },
  { "society_name": "Gaur Greenvista", "latitude": 28.6458, "longitude": 77.3631 },
  { "society_name": "Shipra Suncity Regent", "latitude": 28.6411, "longitude": 77.3685 },
  { "society_name": "GDA Flats Indirapuram", "latitude": 28.6472, "longitude": 77.3595 },
  { "society_name": "JNC Princess Park", "latitude": 28.6481, "longitude": 77.3604 },
  { "society_name": "Arihant Residency", "latitude": 28.6504, "longitude": 77.3578 },
  { "society_name": "Exotica East Square", "latitude": 28.6528, "longitude": 77.3551 },
  { "society_name": "GDA Flats", "latitude": 28.6571, "longitude": 77.4225 },
  { "society_name": "UPAVP Mandola Vihar Apartment", "latitude": 28.7455, "longitude": 77.3112 },
  { "society_name": "GDA Madhuban Bapu Dham Society", "latitude": 28.6811, "longitude": 77.4655 },
  { "society_name": "Rise Organic Homes", "latitude": 28.6631, "longitude": 77.4422 },
  { "society_name": "Mahagun Puram Phase 2", "latitude": 28.6654, "longitude": 77.4395 },
  { "society_name": "Ruchira Sapphire Plaza", "latitude": 28.6678, "longitude": 77.4368 },
  { "society_name": "Parsvnath Paradise", "latitude": 28.6711, "longitude": 77.3512 },
  { "society_name": "Saviour Park", "latitude": 28.6734, "longitude": 77.3485 },
  { "society_name": "Moti Residency", "latitude": 28.6758, "longitude": 77.3458 },
  { "society_name": "Landcraft Golflinks", "latitude": 28.6522, "longitude": 77.4611 },
  { "society_name": "Mahagun Puram", "latitude": 28.6654, "longitude": 77.4395 },
  { "society_name": "Wave Dream Homes", "latitude": 28.6422, "longitude": 77.4855 },
  { "society_name": "Aditya City Apartments", "latitude": 28.6311, "longitude": 77.4955 },
  { "society_name": "Aditya Urban Homes", "latitude": 28.6334, "longitude": 77.4928 },
  { "society_name": "Divyansh Onyx", "latitude": 28.6445, "longitude": 77.4828 },
  { "society_name": "Wave Veridia Oakwood Enclave", "latitude": 28.6468, "longitude": 77.4801 },
  { "society_name": "Urban Homes Aditya World City", "latitude": 28.6311, "longitude": 77.4955 },
  { "society_name": "Aditya City Grace", "latitude": 28.6358, "longitude": 77.4901 },
  { "society_name": "Aditya World City", "latitude": 28.6311, "longitude": 77.4955 },
  { "society_name": "Savfab Jasmine Grove", "latitude": 28.6491, "longitude": 77.4775 },
  { "society_name": "Skardi Greens", "latitude": 28.6514, "longitude": 77.4748 },
  { "society_name": "Wave Executive Floors", "latitude": 28.6422, "longitude": 77.4855 },
  { "society_name": "Parakh The Golden Gate", "latitude": 28.6538, "longitude": 77.4721 },
  { "society_name": "Wave City Dream Homes Ghaziabad", "latitude": 28.6422, "longitude": 77.4855 },
  { "society_name": "VVIP Namah", "latitude": 28.6561, "longitude": 77.4695 },
  { "society_name": "Marina Suites", "latitude": 28.6584, "longitude": 77.4668 },
  { "society_name": "Wave City", "latitude": 28.6422, "longitude": 77.4855 },
  { "society_name": "Wave Swamanorath", "latitude": 28.6435, "longitude": 77.4831 },
  { "society_name": "Sapphire Smart Homes", "latitude": 28.6448, "longitude": 77.4812 },
  { "society_name": "Aditya World City Urban Royal", "latitude": 28.6311, "longitude": 77.4955 },
  { "society_name": "Wave Eligo", "latitude": 28.6461, "longitude": 77.4792 },
  { "society_name": "Unione Residency", "latitude": 28.6474, "longitude": 77.4771 },
  { "society_name": "Agarwal The Resort", "latitude": 28.6488, "longitude": 77.4752 },
  { "society_name": "Landcraft Golf Link Apartments", "latitude": 28.6522, "longitude": 77.4611 },
  { "society_name": "Gaur River View Apartments", "latitude": 28.6555, "longitude": 77.4582 },
  { "society_name": "Supertech Icon", "latitude": 28.6411, "longitude": 77.3685 },
  { "society_name": "V3S Indralok", "latitude": 28.6434, "longitude": 77.3658 },
  { "society_name": "Amrapali Village", "latitude": 28.6574, "longitude": 77.3498 },
  { "society_name": "UPHD Ganga Yamuna and Hindon Apartment", "latitude": 28.6511, "longitude": 77.3385 },
  { "society_name": "VVIP Addresses", "latitude": 28.6755, "longitude": 77.4422 },
  { "society_name": "KW Srishti", "latitude": 28.6778, "longitude": 77.4395 },
  { "society_name": "Eureka Diya Greencity", "latitude": 28.6801, "longitude": 77.4368 },
  { "society_name": "SVP Gulmohur Garden", "latitude": 28.6824, "longitude": 77.4341 },
  { "society_name": "Charms Castle", "latitude": 28.6848, "longitude": 77.4315 },
  { "society_name": "Landcraft River Heights", "latitude": 28.6871, "longitude": 77.4288 },
  { "society_name": "Nilaya Greens", "latitude": 28.6894, "longitude": 77.4261 },
  { "society_name": "Windsor Paradise 2", "latitude": 28.6918, "longitude": 77.4234 },
  { "society_name": "Javin Raj Empire", "latitude": 28.6941, "longitude": 77.4208 },
  { "society_name": "Star Rameshwaram", "latitude": 28.6964, "longitude": 77.4181 },
  { "society_name": "SCC Sapphire", "latitude": 28.6988, "longitude": 77.4154 },
  { "society_name": "Mittal Rajnagar Residency", "latitude": 28.7011, "longitude": 77.4128 },
  { "society_name": "Addela Palm Resort", "latitude": 28.7034, "longitude": 77.4101 },
  { "society_name": "Ajnara Integrity", "latitude": 28.7058, "longitude": 77.4075 },
  { "society_name": "Gaur Cascades", "latitude": 28.7081, "longitude": 77.4048 },
  { "society_name": "Ascent Savy Ville De", "latitude": 28.7104, "longitude": 77.4021 },
  { "society_name": "MCC Signature Heights", "latitude": 28.7128, "longitude": 77.3995 },
  { "society_name": "KDPMGI Gharaunda", "latitude": 28.7151, "longitude": 77.3968 },
  { "society_name": "Shourya Aura Chimera", "latitude": 28.7174, "longitude": 77.3941 },
  { "society_name": "Ashiana Palm Court", "latitude": 28.7198, "longitude": 77.3915 },
  { "society_name": "Aggarwal Heights", "latitude": 28.7221, "longitude": 77.3888 },
  { "society_name": "Emenox Brave Hearts", "latitude": 28.7244, "longitude": 77.3861 },
  { "society_name": "VVIP Mangal", "latitude": 28.7268, "longitude": 77.3835 },
  { "society_name": "SG Grand", "latitude": 28.7291, "longitude": 77.3808 },
  { "society_name": "Meenal Balmukanda Residency", "latitude": 28.7314, "longitude": 77.3781 },
  { "society_name": "Highend Paradise", "latitude": 28.7338, "longitude": 77.3755 },
  { "society_name": "MR Platinum 321", "latitude": 28.7361, "longitude": 77.3728 },
  { "society_name": "Uninav Heights", "latitude": 28.7384, "longitude": 77.3701 },
  { "society_name": "Vasu Fortune Residency", "latitude": 28.7408, "longitude": 77.3675 },
  { "society_name": "Devika Skypers", "latitude": 28.7431, "longitude": 77.3648 },
  { "society_name": "Uninav Utopia", "latitude": 28.7454, "longitude": 77.3621 },
  { "society_name": "KDP Grand Savanna", "latitude": 28.7478, "longitude": 77.3595 },
  { "society_name": "SCC Heights", "latitude": 28.7501, "longitude": 77.3568 },
  { "society_name": "Himalaya Tanishq", "latitude": 28.7524, "longitude": 77.3541 },
  { "society_name": "MR Proview Officer City 2", "latitude": 28.7548, "longitude": 77.3515 },
  { "society_name": "Shree Energy Classic Residency", "latitude": 28.7571, "longitude": 77.3488 },
  { "society_name": "Migsun Roof", "latitude": 28.7594, "longitude": 77.3461 },
  { "society_name": "Sg Impression 58", "latitude": 28.7618, "longitude": 77.3435 },
  { "society_name": "Royce Sentosa Parc", "latitude": 28.7641, "longitude": 77.3408 },
  { "society_name": "LR Bluemoon Homes", "latitude": 28.7664, "longitude": 77.3381 },
  { "society_name": "Techmans Moti Residency", "latitude": 28.7688, "longitude": 77.3355 },
  { "society_name": "Value Meadows Vista", "latitude": 28.7711, "longitude": 77.3328 },
  { "society_name": "Divyansh Arc Angels", "latitude": 28.7734, "longitude": 77.3301 },
  { "society_name": "Proview Officer City", "latitude": 28.7758, "longitude": 77.3275 },
  { "society_name": "KM Residency", "latitude": 28.7781, "longitude": 77.3248 },
  { "society_name": "Mehak Jeevan", "latitude": 28.7804, "longitude": 77.3221 },
  { "society_name": "Uninav Bliss", "latitude": 28.7828, "longitude": 77.3195 },
  { "society_name": "Raj Garden City", "latitude": 28.7851, "longitude": 77.3168 },
  { "society_name": "Ramprastha Colony", "latitude": 28.6655, "longitude": 77.3242 },
  { "society_name": "JM Park Sapphire", "latitude": 28.6678, "longitude": 77.3215 },
  { "society_name": "Ramprastha Pearl Court", "latitude": 28.6655, "longitude": 77.3242 },
  { "society_name": "Ramprastha Platinum Height", "latitude": 28.6672, "longitude": 77.3221 },
  { "society_name": "Gulshan GC Emerald Heights", "latitude": 28.6544, "longitude": 77.3722 },
  { "society_name": "Saviour Greenisle", "latitude": 28.6568, "longitude": 77.3695 },
  { "society_name": "Rishabh Cloud 9 Towers", "latitude": 28.6621, "longitude": 77.3445 },
  { "society_name": "Express Green Apartment Sector 1 Vaishali", "latitude": 28.6422, "longitude": 77.3385 },
  { "society_name": "SKG The Merlin", "latitude": 28.6445, "longitude": 77.3358 },
  { "society_name": "Express One", "latitude": 28.6468, "longitude": 77.3331 },
  { "society_name": "Nandini The Vasundhara Grand", "latitude": 28.6491, "longitude": 77.3304 },
  { "society_name": "Elite Estate", "latitude": 28.6514, "longitude": 77.3278 },
  { "society_name": "Metro Suites Glitz", "latitude": 28.6538, "longitude": 77.3251 },
  { "society_name": "Apex Acacia Valley", "latitude": 28.6561, "longitude": 77.3225 },
  { "society_name": "SG Homes", "latitude": 28.6584, "longitude": 77.3198 },
  { "society_name": "Gardenia Glamour", "latitude": 28.6608, "longitude": 77.3171 },
  { "society_name": "Sarvottam KSN Square", "latitude": 28.6631, "longitude": 77.3144 },
  { "society_name": "JNC Greenwoods", "latitude": 28.6654, "longitude": 77.3118 },
  { "society_name": "Nandini Metro Suites", "latitude": 28.6538, "longitude": 77.3251 },
  { "society_name": "Eldeco Apartments", "latitude": 28.6411, "longitude": 77.3385 },
  { "society_name": "Mahagun Villa", "latitude": 28.6434, "longitude": 77.3358 },
  { "society_name": "Mahagun Mosaic", "latitude": 28.6458, "longitude": 77.3331 },
  { "society_name": "Devika Apartments", "latitude": 28.6481, "longitude": 77.3304 },
  { "society_name": "Surya Kanishk Tower", "latitude": 28.6504, "longitude": 77.3278 },
  { "society_name": "Express Apartments", "latitude": 28.6422, "longitude": 77.3385 },
  { "society_name": "Leela Homes", "latitude": 28.6528, "longitude": 77.3251 },
  { "society_name": "Amrapali Apartments", "latitude": 28.6574, "longitude": 77.3498 },
  { "society_name": "Gaur Heights", "latitude": 28.6551, "longitude": 77.3225 },
  { "society_name": "Gaur Ganga", "latitude": 28.6574, "longitude": 77.3198 },
  { "society_name": "CGHS Vartalok Apartments", "latitude": 28.6598, "longitude": 77.3171 },
  { "society_name": "Supertech Avant Garde", "latitude": 28.6621, "longitude": 77.3144 },
  { "society_name": "Ansals Neelpadam 1", "latitude": 28.6411, "longitude": 77.3385 },
  { "society_name": "Supertech Residency", "latitude": 28.6434, "longitude": 77.3358 },
  { "society_name": "ABA Olive County", "latitude": 28.6688, "longitude": 77.3745 },
  { "society_name": "Civitech Florencia", "latitude": 28.6711, "longitude": 77.3718 },
  { "society_name": "Aditya World City Urban Homes", "latitude": 28.6311, "longitude": 77.4955 },
  { "society_name": "Real World Residency", "latitude": 28.6334, "longitude": 77.4928 },
  { "society_name": "SVP Gulmohar Garden Phase 2", "latitude": 28.6824, "longitude": 77.4341 },
  { "society_name": "shalimargarden ext ii ghaziabad", "latitude": 28.6911, "longitude": 77.3185 },
  { "society_name": "Prateek Grand City", "latitude": 28.6411, "longitude": 77.4285 },
  { "society_name": "Gaurs Siddhartham", "latitude": 28.6434, "longitude": 77.4258 },
  { "society_name": "T Homes", "latitude": 28.6458, "longitude": 77.4231 },
  { "society_name": "SG Shikhar Height", "latitude": 28.6481, "longitude": 77.4204 },
  { "society_name": "T and T Eutopia", "latitude": 28.6504, "longitude": 77.4178 },
  { "society_name": "Apex The Kremlin", "latitude": 28.6528, "longitude": 77.4151 },
  { "society_name": "UPAVP Brahmputra Enclave", "latitude": 28.6551, "longitude": 77.4125 },
  { "society_name": "Siddharth Vihar Residency", "latitude": 28.6411, "longitude": 77.4285 },
  { "society_name": "Truvae Fragrance Homes", "latitude": 28.6574, "longitude": 77.4098 },
  { "society_name": "Saya Gold Avenue", "latitude": 28.6411, "longitude": 77.3712 },
  { "society_name": "Aditya Mega City", "latitude": 28.6434, "longitude": 77.3695 },
  { "society_name": "Krishna Apra Gardens", "latitude": 28.6311, "longitude": 77.3855 },
  { "society_name": "Express Garden", "latitude": 28.6335, "longitude": 77.3828 },
  { "society_name": "Shipra Sun City", "latitude": 28.6411, "longitude": 77.3685 },
  { "society_name": "Mahagun Mansion 1 and 2", "latitude": 28.6458, "longitude": 77.3631 },
  { "society_name": "Amrapali Royal", "latitude": 28.6481, "longitude": 77.3604 },
  { "society_name": "Assotech Windsor Park", "latitude": 28.6381, "longitude": 77.3745 },
  { "society_name": "Gaur Green City", "latitude": 28.6355, "longitude": 77.3712 },
  { "society_name": "Gulshan GC Grand", "latitude": 28.6544, "longitude": 77.3722 },
  { "society_name": "Panchsheel SPS Residency", "latitude": 28.6568, "longitude": 77.3695 },
  { "society_name": "HRC Professional Hub", "latitude": 28.6591, "longitude": 77.3595 },
  { "society_name": "Amrapali Green", "latitude": 28.6574, "longitude": 77.3498 },
  { "society_name": "Aarcity Krishna Apra Sapphire", "latitude": 28.6434, "longitude": 77.3695 },
  { "society_name": "Shipra Neo", "latitude": 28.6411, "longitude": 77.3685 },
  { "society_name": "HRC Apartments", "latitude": 28.6591, "longitude": 77.3595 },
  { "society_name": "Parsvnath Majestic Arcade", "latitude": 28.6458, "longitude": 77.3631 },
  { "society_name": "Ramprastha Greens Royal Park", "latitude": 28.6655, "longitude": 77.3242 },
  { "society_name": "Oasis Emerald Heights", "latitude": 28.7058, "longitude": 77.4075 },
  { "society_name": "Gardenia Gitanjali", "latitude": 28.6551, "longitude": 77.4325 },
  { "society_name": "Ajpa Dronagiri", "latitude": 28.6411, "longitude": 77.4485 },
  { "society_name": "Apex The Florus", "latitude": 28.6528, "longitude": 77.4151 },
  { "society_name": "Migsun Kiaan", "latitude": 28.4788, "longitude": 77.4912 },
  { "society_name": "Sanchar Nest Palm Heights", "latitude": 28.6822, "longitude": 77.4585 },
  { "society_name": "Wave Floors", "latitude": 28.6422, "longitude": 77.4855 },
  { "society_name": "Lotus Srishti", "latitude": 28.6891, "longitude": 77.4504 },
  { "society_name": "Shyam Bankey Bihari Sharnam", "latitude": 28.6778, "longitude": 77.4395 },
  { "society_name": "AR Reflections", "latitude": 28.6918, "longitude": 77.4234 },
  { "society_name": "SG Impressions Plus", "latitude": 28.7618, "longitude": 77.3435 },
  { "society_name": "Milan Earth", "latitude": 28.7011, "longitude": 77.4128 },
  { "society_name": "Ajnara Grace", "latitude": 28.7058, "longitude": 77.4075 },
  { "society_name": "Rama Heights", "latitude": 28.7128, "longitude": 77.3995 },
  { "society_name": "GAV Green View Heights", "latitude": 28.7734, "longitude": 77.3301 },
  { "society_name": "Ashiana Le Residency", "latitude": 28.6631, "longitude": 77.4422 },
  { "society_name": "Kingswood Court", "latitude": 28.6854, "longitude": 77.3978 },
  { "society_name": "Sangwan Heights", "latitude": 28.6871, "longitude": 77.4288 }
]